{"title":"AWS Cloud & Container Mastery","markdown":{"yaml":{"title":"AWS Cloud & Container Mastery","format":{"html":{"include-in-header":{"text":"<link rel=\"preconnect\" href=\"https://fonts.googleapis.com\">\n<link rel=\"preconnect\" href=\"https://fonts.gstatic.com\" crossorigin>\n<link href=\"https://fonts.googleapis.com/css2?family=Cormorant+Garamond:ital,wght@0,400;0,600;0,700;1,400;1,600&family=IBM+Plex+Sans:wght@300;400;500;600&family=IBM+Plex+Mono:wght@400;500&display=swap\" rel=\"stylesheet\">\n"}}},"page-layout":"full"},"containsRefs":false,"markdown":"\n\n```{=html}\n<style>\n/* ═══════════════════════════════════════════════════════════\n   AWS CLOUD MASTERY — Premium Academy · Warm Dark Aesthetic\n   ═══════════════════════════════════════════════════════════ */\n\n:root {\n  --bg:            #0b0b0d;\n  --bg-surface:    #101014;\n  --bg-card:       #15151b;\n  --bg-card-hover: #1a1a22;\n  --bg-elevated:   #1e1e27;\n\n  --orange:        #FF9900;\n  --orange-mid:    #e68a00;\n  --orange-dim:    rgba(255,153,0,0.11);\n  --orange-glow:   rgba(255,153,0,0.22);\n  --orange-border: rgba(255,153,0,0.28);\n\n  --amber:         #fbbf24;\n  --amber-dim:     rgba(251,191,36,0.1);\n\n  --sage:          #6ee7b7;\n  --sage-dim:      rgba(110,231,183,0.1);\n\n  --red:           #f87171;\n  --red-dim:       rgba(248,113,113,0.1);\n\n  --text-primary:  #f2ede4;\n  --text-secondary:#b0a898;\n  --text-muted:    #6b6358;\n  --text-dim:      #33302c;\n\n  --border:        rgba(255,153,0,0.09);\n  --border-mid:    rgba(255,153,0,0.18);\n  --border-bright: rgba(255,153,0,0.32);\n  --border-subtle: rgba(255,255,255,0.05);\n\n  --font-display:  'Cormorant Garamond', Georgia, serif;\n  --font-body:     'IBM Plex Sans', sans-serif;\n  --font-mono:     'IBM Plex Mono', monospace;\n\n  --radius-sm:  4px;\n  --radius-md:  8px;\n  --radius-lg:  14px;\n  --shadow-card: 0 4px 24px rgba(0,0,0,0.4);\n}\n\n*, *::before, *::after { box-sizing: border-box; margin: 0; padding: 0; }\nbody { background: var(--bg) !important; font-family: var(--font-body); }\n#quarto-content { padding: 0 !important; max-width: 100% !important; }\nnav.navbar, footer, .quarto-title-banner { display: none !important; }\na { text-decoration: none; }\n\n/* ── HEX TEXTURE ── */\n.aws-page {\n  position: relative;\n  overflow-x: hidden;\n  background: var(--bg);\n}\n.aws-page::before {\n  content: '';\n  position: fixed; inset: 0; z-index: 0; pointer-events: none;\n  opacity: 0.028;\n  background-image: url(\"data:image/svg+xml,%3Csvg xmlns='http://www.w3.org/2000/svg' width='56' height='100'%3E%3Cpath d='M28 66L0 50V18L28 2l28 16v32z' fill='none' stroke='%23FF9900' stroke-width='1'/%3E%3Cpath d='M28 100L0 84V52l28-16 28 16v32z' fill='none' stroke='%23FF9900' stroke-width='1'/%3E%3C/svg%3E\");\n  background-size: 56px 100px;\n}\n\n/* ═════════════ HERO ═════════════ */\n.hero {\n  position: relative;\n  min-height: 100vh;\n  display: flex; flex-direction: column;\n  justify-content: center;\n  padding: clamp(5rem,10vh,8rem) clamp(1.5rem,7vw,8rem) clamp(4rem,8vh,6rem);\n  overflow: hidden;\n  z-index: 1;\n}\n.hero::after {\n  content: '';\n  position: absolute; top: -20%; right: -10%;\n  width: 70vw; height: 80vh;\n  background: radial-gradient(ellipse, rgba(255,153,0,0.055) 0%, transparent 65%);\n  pointer-events: none;\n  animation: breathe 8s ease-in-out infinite;\n}\n@keyframes breathe {\n  0%,100% { transform: scale(1); opacity: 1; }\n  50%      { transform: scale(1.08); opacity: .7; }\n}\n.hero-glow-2 {\n  position: absolute; bottom: 0; left: -5%;\n  width: 45vw; height: 45vh;\n  background: radial-gradient(ellipse, rgba(110,231,183,0.04) 0%, transparent 65%);\n  pointer-events: none;\n}\n.hero-inner {\n  position: relative; z-index: 2;\n  max-width: 1200px;\n}\n\n.aws-badge {\n  display: inline-flex; align-items: center; gap: .6rem;\n  font-family: var(--font-mono); font-size: .68rem;\n  letter-spacing: .2em; text-transform: uppercase;\n  color: var(--orange);\n  background: var(--orange-dim);\n  border: 1px solid var(--border-mid);\n  padding: .38rem 1rem; border-radius: 100px;\n  margin-bottom: 2.2rem;\n}\n.badge-pulse {\n  width: 7px; height: 7px; border-radius: 50%;\n  background: var(--orange);\n  box-shadow: 0 0 0 0 rgba(255,153,0,.6);\n  animation: ripple 2s ease-out infinite;\n}\n@keyframes ripple {\n  0%   { box-shadow: 0 0 0 0 rgba(255,153,0,.6); }\n  70%  { box-shadow: 0 0 0 8px rgba(255,153,0,0); }\n  100% { box-shadow: 0 0 0 0 rgba(255,153,0,0); }\n}\n\n.hero-title {\n  font-family: var(--font-display) !important;\n  font-size: clamp(3.6rem, 8vw, 7.5rem) !important;\n  font-weight: 700 !important; line-height: 0.96 !important;\n  color: var(--text-primary) !important;\n  letter-spacing: -.02em; margin-bottom: .45em !important;\n  max-width: 14ch;\n}\n.hero-title .line-orange {\n  color: var(--orange);\n  text-shadow: 0 0 60px rgba(255,153,0,0.3);\n}\n.hero-title .line-italic { font-style: italic; color: var(--text-secondary); }\n\n.hero-desc {\n  font-family: var(--font-body); font-weight: 300;\n  font-size: clamp(1rem, 1.6vw, 1.15rem);\n  color: var(--text-secondary); line-height: 1.72;\n  max-width: 52ch; margin-bottom: 1rem;\n}\n.hero-note {\n  font-family: var(--font-mono); font-size: .75rem;\n  color: var(--text-muted); margin-bottom: 3rem;\n  display: flex; align-items: center; gap: .5rem;\n}\n.hero-note::before { content: '//'; color: var(--orange); font-size: .8rem; }\n\n.hero-cta {\n  display: flex; flex-wrap: wrap; gap: 1rem; align-items: center;\n  margin-bottom: 5rem;\n}\n\n.btn-aws {\n  font-family: var(--font-body); font-weight: 600;\n  font-size: .92rem; letter-spacing: .04em;\n  color: #0b0b0d !important;\n  background: var(--orange);\n  padding: .95rem 2.4rem; border-radius: var(--radius-sm);\n  transition: all .22s ease;\n  box-shadow: 0 0 0 0 rgba(255,153,0,.4);\n  display: inline-flex; align-items: center; gap: .5rem;\n}\n.btn-aws:hover {\n  background: var(--amber);\n  box-shadow: 0 0 40px rgba(255,153,0,.4);\n  transform: translateY(-2px);\n}\n.btn-outline-aws {\n  font-family: var(--font-body); font-weight: 500;\n  font-size: .92rem;\n  color: var(--text-secondary) !important;\n  background: transparent;\n  padding: .95rem 2rem; border-radius: var(--radius-sm);\n  border: 1px solid var(--border-subtle);\n  transition: all .22s ease;\n}\n.btn-outline-aws:hover {\n  border-color: var(--border-mid);\n  color: var(--text-primary) !important;\n  background: rgba(255,255,255,.03);\n}\n\n.hero-stats {\n  display: flex; flex-wrap: wrap; gap: 2.5rem;\n}\n.h-stat-num {\n  font-family: var(--font-display);\n  font-size: 2.5rem; font-weight: 700; line-height: 1;\n  color: var(--text-primary); display: block;\n}\n.h-stat-num span { color: var(--orange); }\n.h-stat-label {\n  font-family: var(--font-mono); font-size: .65rem;\n  letter-spacing: .16em; text-transform: uppercase;\n  color: var(--text-muted); margin-top: .3rem; display: block;\n}\n\n.hero-services {\n  position: absolute;\n  right: clamp(2rem,5vw,6rem); top: 50%;\n  transform: translateY(-50%);\n  display: flex; flex-direction: column; gap: .9rem;\n  z-index: 2;\n}\n@media(max-width:1000px) { .hero-services { display: none; } }\n\n.svc-pill {\n  display: flex; align-items: center; gap: .75rem;\n  padding: .8rem 1.2rem;\n  background: var(--bg-card);\n  border: 1px solid var(--border);\n  border-radius: var(--radius-md);\n  font-family: var(--font-mono); font-size: .73rem;\n  color: var(--text-secondary);\n  min-width: 190px;\n  transition: border-color .2s, transform .2s;\n  animation: pillSlide .5s ease both;\n  box-shadow: var(--shadow-card);\n}\n.svc-pill:hover { border-color: var(--orange-border); transform: translateX(-4px); }\n.svc-pill:nth-child(1){animation-delay:.05s}\n.svc-pill:nth-child(2){animation-delay:.12s}\n.svc-pill:nth-child(3){animation-delay:.19s}\n.svc-pill:nth-child(4){animation-delay:.26s}\n.svc-pill:nth-child(5){animation-delay:.33s}\n.svc-pill:nth-child(6){animation-delay:.40s}\n.svc-pill:nth-child(7){animation-delay:.47s}\n\n@keyframes pillSlide {\n  from { opacity: 0; transform: translateX(24px); }\n  to   { opacity: 1; transform: translateX(0); }\n}\n.svc-icon {\n  width: 28px; height: 28px; border-radius: 6px;\n  display: flex; align-items: center; justify-content: center;\n  font-size: .95rem; flex-shrink: 0;\n  background: var(--orange-dim); border: 1px solid rgba(255,153,0,.18);\n}\n.svc-icon.docker { background: rgba(34,193,244,.1); border-color: rgba(34,193,244,.2); }\n.svc-icon.green  { background: var(--sage-dim); border-color: rgba(110,231,183,.2); }\n.svc-icon.red    { background: var(--red-dim); border-color: rgba(248,113,113,.2); }\n.svc-name { color: var(--text-primary); font-weight: 500; }\n.svc-cat  { font-size: .6rem; color: var(--text-muted); letter-spacing: .1em; }\n\n/* ═════════════ STRIP ═════════════ */\n.divider-strip {\n  background: var(--bg-surface);\n  border-top: 1px solid var(--border);\n  border-bottom: 1px solid var(--border);\n  padding: 1.5rem clamp(1.5rem,7vw,8rem);\n  display: flex; align-items: center;\n  gap: 2.5rem; flex-wrap: wrap;\n  position: relative; z-index: 1;\n}\n.strip-item {\n  font-family: var(--font-mono); font-size: .7rem;\n  letter-spacing: .14em; text-transform: uppercase;\n  color: var(--text-muted);\n  display: flex; align-items: center; gap: .5rem;\n}\n.strip-item::before {\n  content: '';\n  width: 4px; height: 4px; border-radius: 50%;\n  background: var(--orange); opacity: .7;\n}\n.strip-divider { flex: 1; height: 1px; background: var(--border); min-width: 20px; }\n@media(max-width:700px) { .strip-divider { display: none; } }\n\n/* ═════════════ SECTION SHELL ═════════════ */\n.s-wrap {\n  padding: clamp(4.5rem,9vw,7rem) clamp(1.5rem,7vw,8rem);\n  position: relative; z-index: 1;\n  max-width: 1400px; margin: 0 auto;\n}\n.s-label {\n  font-family: var(--font-mono); font-size: .67rem;\n  letter-spacing: .24em; text-transform: uppercase;\n  color: var(--orange); margin-bottom: 1rem;\n  display: flex; align-items: center; gap: .7rem;\n}\n.s-label::after {\n  content: ''; display: block; height: 1px; width: 36px;\n  background: linear-gradient(90deg, var(--orange), transparent);\n}\n.s-title {\n  font-family: var(--font-display) !important;\n  font-size: clamp(2.2rem,4.5vw,3.6rem) !important;\n  font-weight: 700 !important; line-height: 1.06 !important;\n  color: var(--text-primary) !important;\n  letter-spacing: -.02em; margin-bottom: .5rem !important;\n}\n.s-title em { font-style: italic; color: var(--orange); }\n.s-desc {\n  font-family: var(--font-body); font-weight: 300;\n  font-size: 1.03rem; color: var(--text-secondary);\n  max-width: 58ch; line-height: 1.72; margin-bottom: 3.5rem;\n}\n\n/* ═════════════ ROADMAP ═════════════ */\n.roadmap-section { background: var(--bg-surface); }\n\n.roadmap {\n  display: grid;\n  grid-template-columns: repeat(5, 1fr);\n  gap: 0; position: relative; margin-top: 3rem;\n}\n@media(max-width:900px) { .roadmap { grid-template-columns: repeat(2,1fr); gap: 1px; } }\n@media(max-width:500px) { .roadmap { grid-template-columns: 1fr; } }\n\n.roadmap::before {\n  content: '';\n  position: absolute;\n  top: 38px; left: calc(10% + 19px); right: calc(10% + 19px);\n  height: 2px;\n  background: linear-gradient(90deg, var(--orange), var(--amber) 50%, var(--sage));\n  opacity: .25; z-index: 0;\n}\n@media(max-width:900px) { .roadmap::before { display: none; } }\n\n.rmap-step {\n  padding: 1.8rem 1.4rem; position: relative; z-index: 1;\n  text-align: center; background: var(--bg-surface);\n  border: 1px solid var(--border);\n  transition: background .25s, border-color .25s; cursor: default;\n  opacity: 0; animation: rIn .5s ease forwards;\n}\n.rmap-step:first-child { border-radius: var(--radius-md) 0 0 var(--radius-md); }\n.rmap-step:last-child  { border-radius: 0 var(--radius-md) var(--radius-md) 0; }\n.rmap-step:hover { background: var(--bg-card-hover); border-color: var(--border-mid); }\n.rmap-step:nth-child(1){animation-delay:.08s}\n.rmap-step:nth-child(2){animation-delay:.18s}\n.rmap-step:nth-child(3){animation-delay:.28s}\n.rmap-step:nth-child(4){animation-delay:.38s}\n.rmap-step:nth-child(5){animation-delay:.48s}\n\n@keyframes rIn {\n  from { opacity: 0; transform: translateY(14px); }\n  to   { opacity: 1; transform: translateY(0); }\n}\n.rmap-num-wrap {\n  width: 38px; height: 38px; border-radius: 50%;\n  margin: 0 auto 1rem;\n  display: flex; align-items: center; justify-content: center;\n  font-family: var(--font-mono); font-size: .75rem; font-weight: 500;\n  background: var(--bg-elevated); border: 2px solid var(--border-mid);\n  color: var(--orange); transition: border-color .25s, box-shadow .25s;\n  position: relative; z-index: 2;\n}\n.rmap-step:hover .rmap-num-wrap {\n  border-color: var(--orange); box-shadow: 0 0 18px rgba(255,153,0,.3);\n}\n.rmap-step.step-final .rmap-num-wrap {\n  background: linear-gradient(135deg, #FF9900, #fbbf24);\n  border-color: transparent; color: #0b0b0d; font-size: .9rem;\n}\n.rmap-title {\n  font-family: var(--font-body); font-weight: 600;\n  font-size: .88rem; color: var(--text-primary); margin-bottom: .4rem; line-height: 1.3;\n}\n.rmap-desc {\n  font-family: var(--font-body); font-weight: 300;\n  font-size: .75rem; color: var(--text-muted); line-height: 1.55;\n}\n.rmap-badge {\n  display: inline-block; margin-top: .6rem;\n  font-family: var(--font-mono); font-size: .6rem;\n  letter-spacing: .12em; text-transform: uppercase;\n  color: var(--orange); background: var(--orange-dim);\n  border: 1px solid rgba(255,153,0,.2); padding: .15rem .5rem; border-radius: 100px;\n}\n.rmap-badge.green { color: var(--sage); background: var(--sage-dim); border-color: rgba(110,231,183,.2); }\n\n/* ═════════════ MODULES ═════════════ */\n.modules-bg { background: var(--bg); }\n\n.modules-grid {\n  display: grid; grid-template-columns: 1fr 1fr;\n  gap: 1px; background: var(--border);\n  border: 1px solid var(--border);\n  border-radius: var(--radius-lg); overflow: hidden;\n}\n@media(max-width:720px) { .modules-grid { grid-template-columns: 1fr; } }\n\n.mod-card {\n  background: var(--bg-card); padding: 2.6rem;\n  position: relative; overflow: hidden;\n  transition: background .3s; cursor: default;\n}\n.mod-card:hover { background: var(--bg-card-hover); }\n\n.mod-card::before {\n  content: '';\n  position: absolute; top: 0; left: 0; right: 0; height: 2px;\n  background: var(--mc-accent, linear-gradient(90deg, var(--orange), var(--amber)));\n  transform: scaleX(0); transform-origin: left; transition: transform .4s ease;\n}\n.mod-card:hover::before { transform: scaleX(1); }\n.mod-card::after {\n  content: '';\n  position: absolute; top: -40px; right: -40px;\n  width: 200px; height: 200px; border-radius: 50%;\n  background: radial-gradient(ellipse, var(--mc-glow, rgba(255,153,0,.05)) 0%, transparent 70%);\n  pointer-events: none; transition: opacity .4s; opacity: 0;\n}\n.mod-card:hover::after { opacity: 1; }\n\n.mc-orange { --mc-accent: linear-gradient(90deg,#FF9900,#fbbf24); --mc-glow: rgba(255,153,0,.06); }\n.mc-sage   { --mc-accent: linear-gradient(90deg,#6ee7b7,#34d399);  --mc-glow: rgba(110,231,183,.05); }\n.mc-blue   { --mc-accent: linear-gradient(90deg,#38bdf8,#67e8f9);  --mc-glow: rgba(56,189,248,.05); }\n.mc-amber  { --mc-accent: linear-gradient(90deg,#fbbf24,#f59e0b);  --mc-glow: rgba(251,191,36,.05); }\n\n.mod-wm {\n  position: absolute; bottom: -14px; right: 8px;\n  font-family: var(--font-display); font-size: 6rem; font-weight: 700;\n  line-height: 1; color: rgba(255,153,0,.04);\n  user-select: none; pointer-events: none; letter-spacing: -.04em;\n}\n.mod-phase {\n  font-family: var(--font-mono); font-size: .62rem;\n  letter-spacing: .18em; text-transform: uppercase;\n  color: var(--text-dim); margin-bottom: .8rem; display: block;\n}\n.mod-head {\n  display: flex; align-items: flex-start; gap: 1rem; margin-bottom: 1.2rem;\n}\n.mod-ico {\n  width: 48px; height: 48px; flex-shrink: 0; border-radius: var(--radius-md);\n  display: flex; align-items: center; justify-content: center; font-size: 1.5rem;\n  background: var(--orange-dim); border: 1px solid rgba(255,153,0,.22);\n}\n.mc-sage  .mod-ico { background: var(--sage-dim); border-color: rgba(110,231,183,.2); }\n.mc-blue  .mod-ico { background: rgba(56,189,248,.08); border-color: rgba(56,189,248,.18); }\n.mc-amber .mod-ico { background: var(--amber-dim); border-color: rgba(251,191,36,.2); }\n\n.mod-num {\n  font-family: var(--font-mono); font-size: .62rem;\n  color: var(--orange); letter-spacing: .12em; margin-bottom: .2rem; display: block;\n}\n.mc-sage .mod-num  { color: var(--sage); }\n.mc-blue .mod-num  { color: #38bdf8; }\n.mc-amber .mod-num { color: var(--amber); }\n\n.mod-name {\n  font-family: var(--font-body); font-size: 1.15rem; font-weight: 600;\n  color: var(--text-primary); line-height: 1.2;\n}\n.mod-desc {\n  font-family: var(--font-body); font-weight: 300;\n  font-size: .9rem; color: var(--text-secondary); line-height: 1.7; margin-bottom: 1.5rem;\n}\n.mod-learns {\n  list-style: none; display: flex; flex-direction: column; gap: .5rem;\n}\n.mod-learns li {\n  font-family: var(--font-body); font-size: .82rem;\n  color: var(--text-muted); font-weight: 400;\n  display: flex; align-items: flex-start; gap: .6rem; line-height: 1.4;\n}\n.mod-learns li::before {\n  content: '▸'; color: var(--orange); font-size: .65rem; margin-top: .15rem; flex-shrink: 0;\n}\n.mc-sage  .mod-learns li::before { color: var(--sage); }\n.mc-blue  .mod-learns li::before { color: #38bdf8; }\n.mc-amber .mod-learns li::before { color: var(--amber); }\n\n.mod-footer {\n  margin-top: 1.8rem; padding-top: 1.2rem;\n  border-top: 1px solid var(--border);\n  display: flex; align-items: center; justify-content: space-between;\n}\n.mod-duration { font-family: var(--font-mono); font-size: .67rem; color: var(--text-dim); letter-spacing: .1em; }\n.mod-level {\n  font-family: var(--font-mono); font-size: .62rem;\n  letter-spacing: .14em; text-transform: uppercase;\n  padding: .2rem .65rem; border-radius: 100px;\n  background: var(--orange-dim); border: 1px solid rgba(255,153,0,.2); color: var(--orange);\n}\n.mc-sage  .mod-level { background: var(--sage-dim); border-color: rgba(110,231,183,.2); color: var(--sage); }\n.mc-blue  .mod-level { background: rgba(56,189,248,.08); border-color: rgba(56,189,248,.18); color: #38bdf8; }\n.mc-amber .mod-level { background: var(--amber-dim); border-color: rgba(251,191,36,.2); color: var(--amber); }\n\n/* ═════════════ AWS SERVICES ═════════════ */\n.services-section { background: var(--bg-surface); }\n\n.svc-categories {\n  display: grid; grid-template-columns: repeat(3,1fr);\n  gap: 1.5rem; margin-top: 3rem;\n}\n@media(max-width:800px) { .svc-categories { grid-template-columns: repeat(2,1fr); } }\n@media(max-width:500px) { .svc-categories { grid-template-columns: 1fr; } }\n\n.svc-cat-card {\n  background: var(--bg-card); border: 1px solid var(--border);\n  border-radius: var(--radius-md); padding: 1.6rem;\n  transition: border-color .25s, transform .25s;\n  opacity: 0; animation: cardIn .5s ease forwards;\n}\n.svc-cat-card:hover { border-color: var(--border-mid); transform: translateY(-3px); }\n.svc-cat-card:nth-child(1){animation-delay:.05s}\n.svc-cat-card:nth-child(2){animation-delay:.12s}\n.svc-cat-card:nth-child(3){animation-delay:.19s}\n.svc-cat-card:nth-child(4){animation-delay:.26s}\n.svc-cat-card:nth-child(5){animation-delay:.33s}\n.svc-cat-card:nth-child(6){animation-delay:.40s}\n\n@keyframes cardIn {\n  from { opacity: 0; transform: translateY(16px); }\n  to   { opacity: 1; transform: translateY(0); }\n}\n.svc-cat-header {\n  display: flex; align-items: center; gap: .7rem;\n  margin-bottom: 1rem; padding-bottom: .8rem; border-bottom: 1px solid var(--border);\n}\n.svc-cat-icon {\n  width: 30px; height: 30px; border-radius: 6px;\n  background: var(--orange-dim); border: 1px solid rgba(255,153,0,.18);\n  display: flex; align-items: center; justify-content: center; font-size: .9rem; flex-shrink: 0;\n}\n.svc-cat-name { font-family: var(--font-body); font-weight: 600; font-size: .82rem; color: var(--text-primary); }\n.svc-list { display: flex; flex-wrap: wrap; gap: .4rem; }\n.svc-tag {\n  font-family: var(--font-mono); font-size: .65rem; color: var(--text-muted);\n  background: rgba(255,255,255,.03); border: 1px solid var(--border-subtle);\n  padding: .2rem .55rem; border-radius: 3px; transition: color .2s, border-color .2s;\n}\n.svc-cat-card:hover .svc-tag { color: var(--orange); border-color: rgba(255,153,0,.2); }\n\n/* ═════════════ PROJECTS ═════════════ */\n.projects-section { background: var(--bg); }\n\n.projects-grid {\n  display: grid; grid-template-columns: repeat(3,1fr);\n  gap: 1.2rem; margin-top: 3rem;\n}\n@media(max-width:800px) { .projects-grid { grid-template-columns: repeat(2,1fr); } }\n@media(max-width:500px) { .projects-grid { grid-template-columns: 1fr; } }\n\n.proj-card {\n  background: var(--bg-card); border: 1px solid var(--border);\n  border-radius: var(--radius-md); padding: 1.8rem;\n  transition: all .25s ease; cursor: default; position: relative; overflow: hidden;\n}\n.proj-card:hover { border-color: var(--border-mid); transform: translateY(-3px); box-shadow: var(--shadow-card); }\n.proj-card::before {\n  content: '';\n  position: absolute; bottom: 0; left: 0; right: 0; height: 1.5px;\n  background: linear-gradient(90deg, transparent, var(--orange), transparent);\n  transform: scaleX(0); transition: transform .35s ease;\n}\n.proj-card:hover::before { transform: scaleX(1); }\n.proj-num { font-family: var(--font-mono); font-size: .62rem; letter-spacing: .18em; text-transform: uppercase; color: var(--text-dim); margin-bottom: .8rem; display: block; }\n.proj-name { font-family: var(--font-body); font-weight: 600; font-size: .95rem; color: var(--text-primary); margin-bottom: .6rem; line-height: 1.3; }\n.proj-desc { font-family: var(--font-body); font-weight: 300; font-size: .8rem; color: var(--text-muted); line-height: 1.6; margin-bottom: 1rem; }\n.proj-tags { display: flex; flex-wrap: wrap; gap: .35rem; }\n.proj-tag { font-family: var(--font-mono); font-size: .6rem; color: var(--orange); background: var(--orange-dim); border: 1px solid rgba(255,153,0,.18); padding: .18rem .5rem; border-radius: 3px; }\n\n/* ═════════════ UPCOMING CSPs ═════════════ */\n.teaser-section { background: var(--bg-surface); border-top: 1px solid var(--border); border-bottom: 1px solid var(--border); }\n.teaser-row { display: flex; flex-wrap: wrap; gap: 1rem; margin-top: 2.5rem; }\n.teaser-card {\n  flex: 1; min-width: 180px; padding: 1.4rem 1.6rem;\n  background: var(--bg-card); border: 1px solid var(--border);\n  border-radius: var(--radius-md); position: relative; overflow: hidden; cursor: default;\n}\n.teaser-card.active { border-color: var(--border-bright); background: var(--bg-elevated); }\n.teaser-card.active::before {\n  content: '';\n  position: absolute; top: 0; left: 0; right: 0; height: 2px;\n  background: linear-gradient(90deg, var(--orange), var(--amber));\n}\n.teaser-card .t-logo { font-family: var(--font-body); font-size: 1.1rem; font-weight: 700; margin-bottom: .3rem; }\n.teaser-card.active .t-logo     { color: var(--orange); }\n.teaser-card:not(.active) .t-logo { color: var(--text-muted); }\n.teaser-card .t-status { font-family: var(--font-mono); font-size: .62rem; letter-spacing: .14em; text-transform: uppercase; }\n.teaser-card.active .t-status     { color: var(--sage); }\n.teaser-card:not(.active) .t-status { color: var(--text-dim); }\n.teaser-card .t-info { font-family: var(--font-body); font-weight: 300; font-size: .78rem; color: var(--text-muted); line-height: 1.5; margin-top: .4rem; }\n\n/* ═════════════ CTA ═════════════ */\n.cta-section {\n  position: relative; overflow: hidden;\n  padding: clamp(5rem,10vw,9rem) clamp(1.5rem,7vw,8rem);\n  text-align: center; background: var(--bg); z-index: 1;\n}\n.cta-section::before {\n  content: ''; position: absolute; inset: 0; pointer-events: none;\n  background:\n    radial-gradient(ellipse 60% 50% at 50% 0%, rgba(255,153,0,.07) 0%, transparent 70%),\n    radial-gradient(ellipse 40% 60% at 20% 100%, rgba(110,231,183,.04) 0%, transparent 60%),\n    radial-gradient(ellipse 40% 60% at 80% 100%, rgba(251,191,36,.04) 0%, transparent 60%);\n}\n.cta-section::after {\n  content: ''; position: absolute; inset: 0; pointer-events: none;\n  background-image: linear-gradient(135deg, transparent 49.5%, rgba(255,153,0,.04) 49.5%, rgba(255,153,0,.04) 50.5%, transparent 50.5%);\n  background-size: 80px 80px; opacity: .5;\n}\n.cta-inner { position: relative; z-index: 2; }\n.cta-eyebrow {\n  display: inline-flex; align-items: center; gap: .6rem;\n  font-family: var(--font-mono); font-size: .68rem;\n  letter-spacing: .2em; text-transform: uppercase;\n  color: var(--orange); background: var(--orange-dim);\n  border: 1px solid var(--border-mid);\n  padding: .38rem 1.1rem; border-radius: 100px; margin-bottom: 2.2rem;\n}\n.cta-title {\n  font-family: var(--font-display) !important;\n  font-size: clamp(2.5rem,6vw,5rem) !important;\n  font-weight: 700 !important; line-height: 1.05 !important;\n  color: var(--text-primary) !important;\n  letter-spacing: -.025em; margin: 0 auto 1.2rem !important; max-width: 22ch;\n}\n.cta-title em { font-style: italic; color: var(--orange); }\n.cta-sub {\n  font-family: var(--font-body); font-weight: 300;\n  font-size: 1.05rem; color: var(--text-secondary);\n  max-width: 48ch; margin: 0 auto 3rem; line-height: 1.7;\n}\n.cta-actions { display: flex; flex-wrap: wrap; gap: 1rem; justify-content: center; }\n\n@media(max-width:700px) {\n  .hero { padding: 5rem 1.5rem 3rem; }\n  .hero-stats { gap: 1.8rem; }\n}\n</style>\n\n<div class=\"aws-page\">\n\n<!-- ══ HERO ══ -->\n<section class=\"hero\">\n  <div class=\"hero-glow-2\"></div>\n  <div class=\"hero-inner\">\n    <div class=\"aws-badge\">\n      <span class=\"badge-pulse\"></span>\n      AWS Cloud Training — Cohort Open\n    </div>\n\n    <h1 class=\"hero-title\">\n      Master<br>\n      <span class=\"line-orange\">Amazon</span><br>\n      <span class=\"line-italic\">Web Services</span>\n    </h1>\n\n    <p class=\"hero-desc\">\n      A structured, practitioner-built program covering cloud fundamentals,\n      core AWS services, Docker containerisation, and production deployment —\n      from absolute zero to job-ready.\n    </p>\n    <div class=\"hero-note\">Starts with cloud basics. No prior experience required.</div>\n\n    <div class=\"hero-cta\">\n      <a href=\"/contact.qmd\" class=\"btn-aws\">\n        <svg width=\"16\" height=\"16\" viewBox=\"0 0 16 16\" fill=\"none\"><path d=\"M3 8h10M9 4l4 4-4 4\" stroke=\"currentColor\" stroke-width=\"1.5\" stroke-linecap=\"round\" stroke-linejoin=\"round\"/></svg>\n        Enroll Now\n      </a>\n      <a href=\"#modules\" class=\"btn-outline-aws\">Browse Curriculum</a>\n    </div>\n\n    <div class=\"hero-stats\">\n      <div class=\"h-stat\">\n        <span class=\"h-stat-num\">5<span>+</span></span>\n        <span class=\"h-stat-label\">Core Modules</span>\n      </div>\n      <div class=\"h-stat\">\n        <span class=\"h-stat-num\">10<span>wk</span></span>\n        <span class=\"h-stat-label\">Program Length</span>\n      </div>\n      <div class=\"h-stat\">\n        <span class=\"h-stat-num\">SAA<span>-C03</span></span>\n        <span class=\"h-stat-label\">Cert Aligned</span>\n      </div>\n    </div>\n  </div>\n\n  <div class=\"hero-services\">\n    <div class=\"svc-pill\"><div class=\"svc-icon\">☁️</div><div><div class=\"svc-name\">EC2</div><div class=\"svc-cat\">Compute</div></div></div>\n    <div class=\"svc-pill\"><div class=\"svc-icon\">🪣</div><div><div class=\"svc-name\">S3</div><div class=\"svc-cat\">Storage</div></div></div>\n    <div class=\"svc-pill\"><div class=\"svc-icon docker\">🐳</div><div><div class=\"svc-name\">Docker</div><div class=\"svc-cat\">Containers</div></div></div>\n    <div class=\"svc-pill\"><div class=\"svc-icon\">🔒</div><div><div class=\"svc-name\">IAM</div><div class=\"svc-cat\">Identity &amp; Access</div></div></div>\n    <div class=\"svc-pill\"><div class=\"svc-icon\">🌐</div><div><div class=\"svc-name\">VPC</div><div class=\"svc-cat\">Networking</div></div></div>\n    <div class=\"svc-pill\"><div class=\"svc-icon green\">λ</div><div><div class=\"svc-name\">Lambda</div><div class=\"svc-cat\">Serverless</div></div></div>\n    <div class=\"svc-pill\"><div class=\"svc-icon red\">🗄️</div><div><div class=\"svc-name\">RDS</div><div class=\"svc-cat\">Databases</div></div></div>\n  </div>\n</section>\n\n<!-- ══ STRIP ══ -->\n<div class=\"divider-strip\">\n  <span class=\"strip-item\">Cloud Fundamentals</span><div class=\"strip-divider\"></div>\n  <span class=\"strip-item\">AWS Core Services</span><div class=\"strip-divider\"></div>\n  <span class=\"strip-item\">Docker &amp; Containers</span><div class=\"strip-divider\"></div>\n  <span class=\"strip-item\">Web Deployment</span><div class=\"strip-divider\"></div>\n  <span class=\"strip-item\">Serverless &amp; Architecture</span>\n</div>\n\n<!-- ══ ROADMAP ══ -->\n<section class=\"roadmap-section\">\n  <div class=\"s-wrap\">\n    <div class=\"s-label\">Learning Path</div>\n    <h2 class=\"s-title\">Your Road to <em>AWS Mastery</em></h2>\n    <p class=\"s-desc\">Five progressive phases — engineered so each week builds directly on the last, from cloud theory to certified practitioner.</p>\n    <div class=\"roadmap\">\n      <div class=\"rmap-step\">\n        <div class=\"rmap-num-wrap\">01</div>\n        <div class=\"rmap-title\">Cloud Computing Fundamentals</div>\n        <div class=\"rmap-desc\">IaaS, PaaS, SaaS, cloud economics, and the why behind cloud migration</div>\n        <span class=\"rmap-badge\">Weeks 1–2</span>\n      </div>\n      <div class=\"rmap-step\">\n        <div class=\"rmap-num-wrap\">02</div>\n        <div class=\"rmap-title\">AWS Core: Compute, Storage &amp; Networking</div>\n        <div class=\"rmap-desc\">EC2, S3, VPC, IAM — launching and securing real infrastructure</div>\n        <span class=\"rmap-badge\">Weeks 3–4</span>\n      </div>\n      <div class=\"rmap-step\">\n        <div class=\"rmap-num-wrap\">03</div>\n        <div class=\"rmap-title\">Docker &amp; Containerisation</div>\n        <div class=\"rmap-desc\">Build images, compose multi-service apps, and push to ECR</div>\n        <span class=\"rmap-badge\">Weeks 5–6</span>\n      </div>\n      <div class=\"rmap-step\">\n        <div class=\"rmap-num-wrap\">04</div>\n        <div class=\"rmap-title\">Web Deployment &amp; Serverless</div>\n        <div class=\"rmap-desc\">Nginx on EC2, SSL, Lambda, API Gateway, and event-driven patterns</div>\n        <span class=\"rmap-badge\">Weeks 7–9</span>\n      </div>\n      <div class=\"rmap-step step-final\">\n        <div class=\"rmap-num-wrap\">✦</div>\n        <div class=\"rmap-title\">Capstone + Certification Prep</div>\n        <div class=\"rmap-desc\">Deploy a full production app and prepare for SAA-C03</div>\n        <span class=\"rmap-badge green\">Week 10 · Cert Ready</span>\n      </div>\n    </div>\n  </div>\n</section>\n\n<!-- ══ MODULES ══ -->\n<section class=\"modules-bg\">\n  <div class=\"s-wrap\" id=\"modules\">\n    <div class=\"s-label\">Curriculum</div>\n    <h2 class=\"s-title\">Five <em>Core Modules</em></h2>\n    <p class=\"s-desc\">Each module is a self-contained, hands-on unit with labs on real AWS infrastructure — not simulated environments.</p>\n\n    <div class=\"modules-grid\">\n\n      <div class=\"mod-card mc-orange\">\n        <div class=\"mod-wm\">01</div>\n        <span class=\"mod-phase\">Module 01 · Foundation</span>\n        <div class=\"mod-head\">\n          <div class=\"mod-ico\">☁️</div>\n          <div><span class=\"mod-num\">Phase 1</span><div class=\"mod-name\">Cloud Computing Fundamentals</div></div>\n        </div>\n        <p class=\"mod-desc\">Build the mental model every cloud practitioner needs. Understand how cloud providers work, what you pay for, and why cloud has replaced on-premise infrastructure in modern engineering.</p>\n        <ul class=\"mod-learns\">\n          <li>IaaS, PaaS &amp; SaaS service models explained</li>\n          <li>Cloud economics: CapEx vs OpEx, pay-as-you-go</li>\n          <li>AWS global infrastructure: Regions &amp; Availability Zones</li>\n          <li>Shared Responsibility Model &amp; compliance basics</li>\n          <li>AWS Management Console, CLI &amp; SDK overview</li>\n        </ul>\n        <div class=\"mod-footer\">\n          <span class=\"mod-duration\">⏱ Weeks 1–2 · ~8 hrs</span>\n          <span class=\"mod-level\">Beginner</span>\n        </div>\n      </div>\n\n      <div class=\"mod-card mc-sage\">\n        <div class=\"mod-wm\">02</div>\n        <span class=\"mod-phase\">Module 02 · AWS Core</span>\n        <div class=\"mod-head\">\n          <div class=\"mod-ico\">⚙️</div>\n          <div><span class=\"mod-num\">Phase 2</span><div class=\"mod-name\">AWS Compute, Storage &amp; Networking</div></div>\n        </div>\n        <p class=\"mod-desc\">Get hands on with the services that power 70% of cloud workloads. Launch EC2 instances, configure secure networks, store objects in S3, and lock everything down with IAM.</p>\n        <ul class=\"mod-learns\">\n          <li>EC2: instance types, AMIs, user-data, key pairs</li>\n          <li>S3: buckets, policies, versioning &amp; static hosting</li>\n          <li>VPC: subnets, route tables, internet &amp; NAT gateways</li>\n          <li>Security Groups &amp; NACLs for layered defence</li>\n          <li>IAM: users, roles, policies &amp; least-privilege design</li>\n        </ul>\n        <div class=\"mod-footer\">\n          <span class=\"mod-duration\">⏱ Weeks 3–4 · ~10 hrs</span>\n          <span class=\"mod-level\">Intermediate</span>\n        </div>\n      </div>\n\n      <div class=\"mod-card mc-blue\">\n        <div class=\"mod-wm\">03</div>\n        <span class=\"mod-phase\">Module 03 · Containers</span>\n        <div class=\"mod-head\">\n          <div class=\"mod-ico\">🐳</div>\n          <div><span class=\"mod-num\">Phase 3</span><div class=\"mod-name\">Docker &amp; Containerisation on AWS</div></div>\n        </div>\n        <p class=\"mod-desc\">Package your applications once, run them anywhere. Master Docker from first principles and integrate containers natively into the AWS ecosystem using ECR and ECS.</p>\n        <ul class=\"mod-learns\">\n          <li>Docker architecture: images, containers &amp; volumes</li>\n          <li>Writing production-grade Dockerfiles &amp; .dockerignore</li>\n          <li>Docker Compose for multi-container local dev</li>\n          <li>Amazon ECR: building, tagging &amp; pushing images</li>\n          <li>Introduction to ECS &amp; Fargate for managed containers</li>\n        </ul>\n        <div class=\"mod-footer\">\n          <span class=\"mod-duration\">⏱ Weeks 5–6 · ~10 hrs</span>\n          <span class=\"mod-level\">Intermediate</span>\n        </div>\n      </div>\n\n      <div class=\"mod-card mc-amber\">\n        <div class=\"mod-wm\">04</div>\n        <span class=\"mod-phase\">Module 04 · Deployment</span>\n        <div class=\"mod-head\">\n          <div class=\"mod-ico\">🌐</div>\n          <div><span class=\"mod-num\">Phase 4</span><div class=\"mod-name\">Web Deployment, SSL &amp; Serverless</div></div>\n        </div>\n        <p class=\"mod-desc\">Take real applications live. Configure Nginx as a reverse proxy on EC2, automate SSL with Let's Encrypt, build serverless APIs with Lambda, and connect services with event-driven patterns.</p>\n        <ul class=\"mod-learns\">\n          <li>Nginx reverse proxy &amp; virtual host configuration</li>\n          <li>SSL/TLS with Certbot + Let's Encrypt on EC2</li>\n          <li>Route 53: DNS, A/CNAME records &amp; health checks</li>\n          <li>AWS Lambda: writing, deploying &amp; testing functions</li>\n          <li>API Gateway: REST APIs, triggers &amp; CORS setup</li>\n        </ul>\n        <div class=\"mod-footer\">\n          <span class=\"mod-duration\">⏱ Weeks 7–8 · ~10 hrs</span>\n          <span class=\"mod-level\">Intermediate</span>\n        </div>\n      </div>\n\n      <div class=\"mod-card mc-orange\" style=\"grid-column: 1 / -1;\">\n        <div class=\"mod-wm\" style=\"font-size:8rem;right:20px;\">05</div>\n        <span class=\"mod-phase\">Module 05 · Architecture</span>\n        <div class=\"mod-head\">\n          <div class=\"mod-ico\">🏗️</div>\n          <div><span class=\"mod-num\">Phase 5 · Capstone</span><div class=\"mod-name\">Cloud Architecture, Databases &amp; Certification Prep</div></div>\n        </div>\n        <div style=\"display:grid;grid-template-columns:1fr 1fr;gap:2rem;flex-wrap:wrap;\">\n          <p class=\"mod-desc\">Tie everything together. Design scalable, fault-tolerant architectures using AWS Well-Architected Framework pillars. Add managed databases, caching, and monitoring — then build a complete capstone project from scratch.</p>\n          <ul class=\"mod-learns\">\n            <li>RDS (PostgreSQL / MySQL) setup, backups &amp; replicas</li>\n            <li>ElastiCache &amp; DynamoDB for high-performance data</li>\n            <li>Load Balancers &amp; Auto Scaling Groups</li>\n            <li>CloudWatch metrics, alarms &amp; logging</li>\n            <li>Well-Architected Framework: 6 pillars review</li>\n            <li>SAA-C03 exam strategy &amp; mock assessment</li>\n          </ul>\n        </div>\n        <div class=\"mod-footer\" style=\"margin-top:1.4rem;\">\n          <span class=\"mod-duration\">⏱ Weeks 9–10 · ~12 hrs</span>\n          <span class=\"mod-level\">Advanced</span>\n        </div>\n      </div>\n\n    </div>\n  </div>\n</section>\n\n<!-- ══ AWS SERVICES ══ -->\n<section class=\"services-section\">\n  <div class=\"s-wrap\">\n    <div class=\"s-label\">Services</div>\n    <h2 class=\"s-title\">AWS Services You'll <em>Use</em></h2>\n    <p class=\"s-desc\">Hands-on labs with the most in-demand AWS services — grouped by category so you understand how they interconnect.</p>\n\n    <div class=\"svc-categories\">\n      <div class=\"svc-cat-card\">\n        <div class=\"svc-cat-header\"><div class=\"svc-cat-icon\">⚡</div><span class=\"svc-cat-name\">Compute</span></div>\n        <div class=\"svc-list\"><span class=\"svc-tag\">EC2</span><span class=\"svc-tag\">Lambda</span><span class=\"svc-tag\">ECS Fargate</span><span class=\"svc-tag\">Elastic Beanstalk</span><span class=\"svc-tag\">Auto Scaling</span></div>\n      </div>\n      <div class=\"svc-cat-card\">\n        <div class=\"svc-cat-header\"><div class=\"svc-cat-icon\">🗃️</div><span class=\"svc-cat-name\">Storage &amp; Databases</span></div>\n        <div class=\"svc-list\"><span class=\"svc-tag\">S3</span><span class=\"svc-tag\">EBS</span><span class=\"svc-tag\">RDS</span><span class=\"svc-tag\">DynamoDB</span><span class=\"svc-tag\">ElastiCache</span></div>\n      </div>\n      <div class=\"svc-cat-card\">\n        <div class=\"svc-cat-header\"><div class=\"svc-cat-icon\">🌐</div><span class=\"svc-cat-name\">Networking</span></div>\n        <div class=\"svc-list\"><span class=\"svc-tag\">VPC</span><span class=\"svc-tag\">Route 53</span><span class=\"svc-tag\">ALB / NLB</span><span class=\"svc-tag\">CloudFront</span><span class=\"svc-tag\">API Gateway</span></div>\n      </div>\n      <div class=\"svc-cat-card\">\n        <div class=\"svc-cat-header\"><div class=\"svc-cat-icon\">🔒</div><span class=\"svc-cat-name\">Security &amp; Identity</span></div>\n        <div class=\"svc-list\"><span class=\"svc-tag\">IAM</span><span class=\"svc-tag\">Security Groups</span><span class=\"svc-tag\">NACLs</span><span class=\"svc-tag\">KMS</span><span class=\"svc-tag\">Secrets Manager</span></div>\n      </div>\n      <div class=\"svc-cat-card\">\n        <div class=\"svc-cat-header\"><div class=\"svc-cat-icon\">📊</div><span class=\"svc-cat-name\">Monitoring &amp; Ops</span></div>\n        <div class=\"svc-list\"><span class=\"svc-tag\">CloudWatch</span><span class=\"svc-tag\">CloudTrail</span><span class=\"svc-tag\">AWS Config</span><span class=\"svc-tag\">SNS</span><span class=\"svc-tag\">SQS</span></div>\n      </div>\n      <div class=\"svc-cat-card\">\n        <div class=\"svc-cat-header\"><div class=\"svc-cat-icon\">🐳</div><span class=\"svc-cat-name\">Containers</span></div>\n        <div class=\"svc-list\"><span class=\"svc-tag\">Docker</span><span class=\"svc-tag\">ECR</span><span class=\"svc-tag\">ECS</span><span class=\"svc-tag\">Fargate</span><span class=\"svc-tag\">Docker Compose</span></div>\n      </div>\n    </div>\n  </div>\n</section>\n\n<!-- ══ PROJECTS ══ -->\n<section class=\"projects-section\">\n  <div class=\"s-wrap\">\n    <div class=\"s-label\">Hands-On Projects</div>\n    <h2 class=\"s-title\">Build <em>Real Things</em></h2>\n    <p class=\"s-desc\">Every module culminates in a project deployed to live AWS infrastructure — not sandboxed demos.</p>\n\n    <div class=\"projects-grid\">\n      <div class=\"proj-card\">\n        <span class=\"proj-num\">Project 01</span>\n        <div class=\"proj-name\">Secure Multi-Tier VPC Architecture</div>\n        <div class=\"proj-desc\">Design and deploy a VPC with public/private subnets, NAT gateways, bastion host, and security group rules mirroring production setups.</div>\n        <div class=\"proj-tags\"><span class=\"proj-tag\">VPC</span><span class=\"proj-tag\">EC2</span><span class=\"proj-tag\">IAM</span></div>\n      </div>\n      <div class=\"proj-card\">\n        <span class=\"proj-num\">Project 02</span>\n        <div class=\"proj-name\">Containerised App on ECS Fargate</div>\n        <div class=\"proj-desc\">Dockerise a web application, push to ECR, and deploy as a managed ECS Fargate service behind an Application Load Balancer.</div>\n        <div class=\"proj-tags\"><span class=\"proj-tag\">Docker</span><span class=\"proj-tag\">ECR</span><span class=\"proj-tag\">ECS</span></div>\n      </div>\n      <div class=\"proj-card\">\n        <span class=\"proj-num\">Project 03</span>\n        <div class=\"proj-name\">Full-Stack Serverless API</div>\n        <div class=\"proj-desc\">Build a REST API using Lambda + API Gateway backed by DynamoDB, with IAM-secured endpoints, CloudWatch logging, and a custom domain via Route 53.</div>\n        <div class=\"proj-tags\"><span class=\"proj-tag\">Lambda</span><span class=\"proj-tag\">API Gateway</span><span class=\"proj-tag\">DynamoDB</span></div>\n      </div>\n      <div class=\"proj-card\">\n        <span class=\"proj-num\">Project 04</span>\n        <div class=\"proj-name\">Static Website with CDN &amp; SSL</div>\n        <div class=\"proj-desc\">Host a static site on S3, front it with CloudFront for global CDN, attach an ACM SSL certificate, and configure Route 53 DNS.</div>\n        <div class=\"proj-tags\"><span class=\"proj-tag\">S3</span><span class=\"proj-tag\">CloudFront</span><span class=\"proj-tag\">Route 53</span></div>\n      </div>\n      <div class=\"proj-card\">\n        <span class=\"proj-num\">Project 05</span>\n        <div class=\"proj-name\">Auto-Scaling Web Application</div>\n        <div class=\"proj-desc\">Deploy a web app across multiple AZs with an ALB, Auto Scaling Group with launch templates, RDS Multi-AZ, and CloudWatch alarms.</div>\n        <div class=\"proj-tags\"><span class=\"proj-tag\">ALB</span><span class=\"proj-tag\">ASG</span><span class=\"proj-tag\">RDS</span></div>\n      </div>\n      <div class=\"proj-card\">\n        <span class=\"proj-num\">Capstone</span>\n        <div class=\"proj-name\">Production-Grade Cloud Platform</div>\n        <div class=\"proj-desc\">Synthesise all five modules into a single full-stack platform: containers, databases, serverless functions, monitoring, and CI/CD basics.</div>\n        <div class=\"proj-tags\"><span class=\"proj-tag\">Full Stack</span><span class=\"proj-tag\">Portfolio</span><span class=\"proj-tag\">SAA-C03</span></div>\n      </div>\n    </div>\n  </div>\n</section>\n\n<!-- ══ UPCOMING CSPs ══ -->\n<section class=\"teaser-section\">\n  <div class=\"s-wrap\">\n    <div class=\"s-label\">Coming Soon</div>\n    <h2 class=\"s-title\">More <em>Cloud Providers</em> on the Way</h2>\n    <p class=\"s-desc\">AWS is just the beginning. Dedicated tracks for Google Cloud and Azure are currently being developed — with the same hands-on, practitioner-first approach.</p>\n    <div class=\"teaser-row\">\n      <div class=\"teaser-card active\">\n        <div class=\"t-logo\">Amazon Web Services</div>\n        <div class=\"t-status\">● Now Enrolling</div>\n        <div class=\"t-info\">Full curriculum live. Certification aligned to SAA-C03.</div>\n      </div>\n      <div class=\"teaser-card\">\n        <div class=\"t-logo\">Google Cloud Platform</div>\n        <div class=\"t-status\">◌ In Development</div>\n        <div class=\"t-info\">GCP Associate Cloud Engineer track — launching soon.</div>\n      </div>\n      <div class=\"teaser-card\">\n        <div class=\"t-logo\">Microsoft Azure</div>\n        <div class=\"t-status\">◌ Planned</div>\n        <div class=\"t-info\">AZ-900 &amp; AZ-104 aligned track coming later this year.</div>\n      </div>\n      <div class=\"teaser-card\">\n        <div class=\"t-logo\">Multi-Cloud Architecture</div>\n        <div class=\"t-status\">◌ Advanced Track</div>\n        <div class=\"t-info\">Advanced course on designing for multiple CSPs simultaneously.</div>\n      </div>\n    </div>\n  </div>\n</section>\n\n<!-- ══ CTA ══ -->\n<section class=\"cta-section\">\n  <div class=\"cta-inner\">\n    <div class=\"cta-eyebrow\"><span class=\"badge-pulse\"></span>Limited Seats Per Cohort</div>\n    <h2 class=\"cta-title\">Your first AWS project<br>goes live <em>this month.</em></h2>\n    <p class=\"cta-sub\">Structured training, real infrastructure, live projects you can put in a portfolio — and a clear path to your first AWS certification.</p>\n    <div class=\"cta-actions\">\n      <a href=\"/contact.qmd\" class=\"btn-aws\">\n        <svg width=\"16\" height=\"16\" viewBox=\"0 0 16 16\" fill=\"none\"><path d=\"M3 8h10M9 4l4 4-4 4\" stroke=\"currentColor\" stroke-width=\"1.5\" stroke-linecap=\"round\" stroke-linejoin=\"round\"/></svg>\n        Enroll in AWS Track\n      </a>\n      <a href=\"/contact.qmd\" class=\"btn-outline-aws\">Talk to an Advisor</a>\n    </div>\n  </div>\n</section>\n\n</div>\n```\n","srcMarkdownNoYaml":"\n\n```{=html}\n<style>\n/* ═══════════════════════════════════════════════════════════\n   AWS CLOUD MASTERY — Premium Academy · Warm Dark Aesthetic\n   ═══════════════════════════════════════════════════════════ */\n\n:root {\n  --bg:            #0b0b0d;\n  --bg-surface:    #101014;\n  --bg-card:       #15151b;\n  --bg-card-hover: #1a1a22;\n  --bg-elevated:   #1e1e27;\n\n  --orange:        #FF9900;\n  --orange-mid:    #e68a00;\n  --orange-dim:    rgba(255,153,0,0.11);\n  --orange-glow:   rgba(255,153,0,0.22);\n  --orange-border: rgba(255,153,0,0.28);\n\n  --amber:         #fbbf24;\n  --amber-dim:     rgba(251,191,36,0.1);\n\n  --sage:          #6ee7b7;\n  --sage-dim:      rgba(110,231,183,0.1);\n\n  --red:           #f87171;\n  --red-dim:       rgba(248,113,113,0.1);\n\n  --text-primary:  #f2ede4;\n  --text-secondary:#b0a898;\n  --text-muted:    #6b6358;\n  --text-dim:      #33302c;\n\n  --border:        rgba(255,153,0,0.09);\n  --border-mid:    rgba(255,153,0,0.18);\n  --border-bright: rgba(255,153,0,0.32);\n  --border-subtle: rgba(255,255,255,0.05);\n\n  --font-display:  'Cormorant Garamond', Georgia, serif;\n  --font-body:     'IBM Plex Sans', sans-serif;\n  --font-mono:     'IBM Plex Mono', monospace;\n\n  --radius-sm:  4px;\n  --radius-md:  8px;\n  --radius-lg:  14px;\n  --shadow-card: 0 4px 24px rgba(0,0,0,0.4);\n}\n\n*, *::before, *::after { box-sizing: border-box; margin: 0; padding: 0; }\nbody { background: var(--bg) !important; font-family: var(--font-body); }\n#quarto-content { padding: 0 !important; max-width: 100% !important; }\nnav.navbar, footer, .quarto-title-banner { display: none !important; }\na { text-decoration: none; }\n\n/* ── HEX TEXTURE ── */\n.aws-page {\n  position: relative;\n  overflow-x: hidden;\n  background: var(--bg);\n}\n.aws-page::before {\n  content: '';\n  position: fixed; inset: 0; z-index: 0; pointer-events: none;\n  opacity: 0.028;\n  background-image: url(\"data:image/svg+xml,%3Csvg xmlns='http://www.w3.org/2000/svg' width='56' height='100'%3E%3Cpath d='M28 66L0 50V18L28 2l28 16v32z' fill='none' stroke='%23FF9900' stroke-width='1'/%3E%3Cpath d='M28 100L0 84V52l28-16 28 16v32z' fill='none' stroke='%23FF9900' stroke-width='1'/%3E%3C/svg%3E\");\n  background-size: 56px 100px;\n}\n\n/* ═════════════ HERO ═════════════ */\n.hero {\n  position: relative;\n  min-height: 100vh;\n  display: flex; flex-direction: column;\n  justify-content: center;\n  padding: clamp(5rem,10vh,8rem) clamp(1.5rem,7vw,8rem) clamp(4rem,8vh,6rem);\n  overflow: hidden;\n  z-index: 1;\n}\n.hero::after {\n  content: '';\n  position: absolute; top: -20%; right: -10%;\n  width: 70vw; height: 80vh;\n  background: radial-gradient(ellipse, rgba(255,153,0,0.055) 0%, transparent 65%);\n  pointer-events: none;\n  animation: breathe 8s ease-in-out infinite;\n}\n@keyframes breathe {\n  0%,100% { transform: scale(1); opacity: 1; }\n  50%      { transform: scale(1.08); opacity: .7; }\n}\n.hero-glow-2 {\n  position: absolute; bottom: 0; left: -5%;\n  width: 45vw; height: 45vh;\n  background: radial-gradient(ellipse, rgba(110,231,183,0.04) 0%, transparent 65%);\n  pointer-events: none;\n}\n.hero-inner {\n  position: relative; z-index: 2;\n  max-width: 1200px;\n}\n\n.aws-badge {\n  display: inline-flex; align-items: center; gap: .6rem;\n  font-family: var(--font-mono); font-size: .68rem;\n  letter-spacing: .2em; text-transform: uppercase;\n  color: var(--orange);\n  background: var(--orange-dim);\n  border: 1px solid var(--border-mid);\n  padding: .38rem 1rem; border-radius: 100px;\n  margin-bottom: 2.2rem;\n}\n.badge-pulse {\n  width: 7px; height: 7px; border-radius: 50%;\n  background: var(--orange);\n  box-shadow: 0 0 0 0 rgba(255,153,0,.6);\n  animation: ripple 2s ease-out infinite;\n}\n@keyframes ripple {\n  0%   { box-shadow: 0 0 0 0 rgba(255,153,0,.6); }\n  70%  { box-shadow: 0 0 0 8px rgba(255,153,0,0); }\n  100% { box-shadow: 0 0 0 0 rgba(255,153,0,0); }\n}\n\n.hero-title {\n  font-family: var(--font-display) !important;\n  font-size: clamp(3.6rem, 8vw, 7.5rem) !important;\n  font-weight: 700 !important; line-height: 0.96 !important;\n  color: var(--text-primary) !important;\n  letter-spacing: -.02em; margin-bottom: .45em !important;\n  max-width: 14ch;\n}\n.hero-title .line-orange {\n  color: var(--orange);\n  text-shadow: 0 0 60px rgba(255,153,0,0.3);\n}\n.hero-title .line-italic { font-style: italic; color: var(--text-secondary); }\n\n.hero-desc {\n  font-family: var(--font-body); font-weight: 300;\n  font-size: clamp(1rem, 1.6vw, 1.15rem);\n  color: var(--text-secondary); line-height: 1.72;\n  max-width: 52ch; margin-bottom: 1rem;\n}\n.hero-note {\n  font-family: var(--font-mono); font-size: .75rem;\n  color: var(--text-muted); margin-bottom: 3rem;\n  display: flex; align-items: center; gap: .5rem;\n}\n.hero-note::before { content: '//'; color: var(--orange); font-size: .8rem; }\n\n.hero-cta {\n  display: flex; flex-wrap: wrap; gap: 1rem; align-items: center;\n  margin-bottom: 5rem;\n}\n\n.btn-aws {\n  font-family: var(--font-body); font-weight: 600;\n  font-size: .92rem; letter-spacing: .04em;\n  color: #0b0b0d !important;\n  background: var(--orange);\n  padding: .95rem 2.4rem; border-radius: var(--radius-sm);\n  transition: all .22s ease;\n  box-shadow: 0 0 0 0 rgba(255,153,0,.4);\n  display: inline-flex; align-items: center; gap: .5rem;\n}\n.btn-aws:hover {\n  background: var(--amber);\n  box-shadow: 0 0 40px rgba(255,153,0,.4);\n  transform: translateY(-2px);\n}\n.btn-outline-aws {\n  font-family: var(--font-body); font-weight: 500;\n  font-size: .92rem;\n  color: var(--text-secondary) !important;\n  background: transparent;\n  padding: .95rem 2rem; border-radius: var(--radius-sm);\n  border: 1px solid var(--border-subtle);\n  transition: all .22s ease;\n}\n.btn-outline-aws:hover {\n  border-color: var(--border-mid);\n  color: var(--text-primary) !important;\n  background: rgba(255,255,255,.03);\n}\n\n.hero-stats {\n  display: flex; flex-wrap: wrap; gap: 2.5rem;\n}\n.h-stat-num {\n  font-family: var(--font-display);\n  font-size: 2.5rem; font-weight: 700; line-height: 1;\n  color: var(--text-primary); display: block;\n}\n.h-stat-num span { color: var(--orange); }\n.h-stat-label {\n  font-family: var(--font-mono); font-size: .65rem;\n  letter-spacing: .16em; text-transform: uppercase;\n  color: var(--text-muted); margin-top: .3rem; display: block;\n}\n\n.hero-services {\n  position: absolute;\n  right: clamp(2rem,5vw,6rem); top: 50%;\n  transform: translateY(-50%);\n  display: flex; flex-direction: column; gap: .9rem;\n  z-index: 2;\n}\n@media(max-width:1000px) { .hero-services { display: none; } }\n\n.svc-pill {\n  display: flex; align-items: center; gap: .75rem;\n  padding: .8rem 1.2rem;\n  background: var(--bg-card);\n  border: 1px solid var(--border);\n  border-radius: var(--radius-md);\n  font-family: var(--font-mono); font-size: .73rem;\n  color: var(--text-secondary);\n  min-width: 190px;\n  transition: border-color .2s, transform .2s;\n  animation: pillSlide .5s ease both;\n  box-shadow: var(--shadow-card);\n}\n.svc-pill:hover { border-color: var(--orange-border); transform: translateX(-4px); }\n.svc-pill:nth-child(1){animation-delay:.05s}\n.svc-pill:nth-child(2){animation-delay:.12s}\n.svc-pill:nth-child(3){animation-delay:.19s}\n.svc-pill:nth-child(4){animation-delay:.26s}\n.svc-pill:nth-child(5){animation-delay:.33s}\n.svc-pill:nth-child(6){animation-delay:.40s}\n.svc-pill:nth-child(7){animation-delay:.47s}\n\n@keyframes pillSlide {\n  from { opacity: 0; transform: translateX(24px); }\n  to   { opacity: 1; transform: translateX(0); }\n}\n.svc-icon {\n  width: 28px; height: 28px; border-radius: 6px;\n  display: flex; align-items: center; justify-content: center;\n  font-size: .95rem; flex-shrink: 0;\n  background: var(--orange-dim); border: 1px solid rgba(255,153,0,.18);\n}\n.svc-icon.docker { background: rgba(34,193,244,.1); border-color: rgba(34,193,244,.2); }\n.svc-icon.green  { background: var(--sage-dim); border-color: rgba(110,231,183,.2); }\n.svc-icon.red    { background: var(--red-dim); border-color: rgba(248,113,113,.2); }\n.svc-name { color: var(--text-primary); font-weight: 500; }\n.svc-cat  { font-size: .6rem; color: var(--text-muted); letter-spacing: .1em; }\n\n/* ═════════════ STRIP ═════════════ */\n.divider-strip {\n  background: var(--bg-surface);\n  border-top: 1px solid var(--border);\n  border-bottom: 1px solid var(--border);\n  padding: 1.5rem clamp(1.5rem,7vw,8rem);\n  display: flex; align-items: center;\n  gap: 2.5rem; flex-wrap: wrap;\n  position: relative; z-index: 1;\n}\n.strip-item {\n  font-family: var(--font-mono); font-size: .7rem;\n  letter-spacing: .14em; text-transform: uppercase;\n  color: var(--text-muted);\n  display: flex; align-items: center; gap: .5rem;\n}\n.strip-item::before {\n  content: '';\n  width: 4px; height: 4px; border-radius: 50%;\n  background: var(--orange); opacity: .7;\n}\n.strip-divider { flex: 1; height: 1px; background: var(--border); min-width: 20px; }\n@media(max-width:700px) { .strip-divider { display: none; } }\n\n/* ═════════════ SECTION SHELL ═════════════ */\n.s-wrap {\n  padding: clamp(4.5rem,9vw,7rem) clamp(1.5rem,7vw,8rem);\n  position: relative; z-index: 1;\n  max-width: 1400px; margin: 0 auto;\n}\n.s-label {\n  font-family: var(--font-mono); font-size: .67rem;\n  letter-spacing: .24em; text-transform: uppercase;\n  color: var(--orange); margin-bottom: 1rem;\n  display: flex; align-items: center; gap: .7rem;\n}\n.s-label::after {\n  content: ''; display: block; height: 1px; width: 36px;\n  background: linear-gradient(90deg, var(--orange), transparent);\n}\n.s-title {\n  font-family: var(--font-display) !important;\n  font-size: clamp(2.2rem,4.5vw,3.6rem) !important;\n  font-weight: 700 !important; line-height: 1.06 !important;\n  color: var(--text-primary) !important;\n  letter-spacing: -.02em; margin-bottom: .5rem !important;\n}\n.s-title em { font-style: italic; color: var(--orange); }\n.s-desc {\n  font-family: var(--font-body); font-weight: 300;\n  font-size: 1.03rem; color: var(--text-secondary);\n  max-width: 58ch; line-height: 1.72; margin-bottom: 3.5rem;\n}\n\n/* ═════════════ ROADMAP ═════════════ */\n.roadmap-section { background: var(--bg-surface); }\n\n.roadmap {\n  display: grid;\n  grid-template-columns: repeat(5, 1fr);\n  gap: 0; position: relative; margin-top: 3rem;\n}\n@media(max-width:900px) { .roadmap { grid-template-columns: repeat(2,1fr); gap: 1px; } }\n@media(max-width:500px) { .roadmap { grid-template-columns: 1fr; } }\n\n.roadmap::before {\n  content: '';\n  position: absolute;\n  top: 38px; left: calc(10% + 19px); right: calc(10% + 19px);\n  height: 2px;\n  background: linear-gradient(90deg, var(--orange), var(--amber) 50%, var(--sage));\n  opacity: .25; z-index: 0;\n}\n@media(max-width:900px) { .roadmap::before { display: none; } }\n\n.rmap-step {\n  padding: 1.8rem 1.4rem; position: relative; z-index: 1;\n  text-align: center; background: var(--bg-surface);\n  border: 1px solid var(--border);\n  transition: background .25s, border-color .25s; cursor: default;\n  opacity: 0; animation: rIn .5s ease forwards;\n}\n.rmap-step:first-child { border-radius: var(--radius-md) 0 0 var(--radius-md); }\n.rmap-step:last-child  { border-radius: 0 var(--radius-md) var(--radius-md) 0; }\n.rmap-step:hover { background: var(--bg-card-hover); border-color: var(--border-mid); }\n.rmap-step:nth-child(1){animation-delay:.08s}\n.rmap-step:nth-child(2){animation-delay:.18s}\n.rmap-step:nth-child(3){animation-delay:.28s}\n.rmap-step:nth-child(4){animation-delay:.38s}\n.rmap-step:nth-child(5){animation-delay:.48s}\n\n@keyframes rIn {\n  from { opacity: 0; transform: translateY(14px); }\n  to   { opacity: 1; transform: translateY(0); }\n}\n.rmap-num-wrap {\n  width: 38px; height: 38px; border-radius: 50%;\n  margin: 0 auto 1rem;\n  display: flex; align-items: center; justify-content: center;\n  font-family: var(--font-mono); font-size: .75rem; font-weight: 500;\n  background: var(--bg-elevated); border: 2px solid var(--border-mid);\n  color: var(--orange); transition: border-color .25s, box-shadow .25s;\n  position: relative; z-index: 2;\n}\n.rmap-step:hover .rmap-num-wrap {\n  border-color: var(--orange); box-shadow: 0 0 18px rgba(255,153,0,.3);\n}\n.rmap-step.step-final .rmap-num-wrap {\n  background: linear-gradient(135deg, #FF9900, #fbbf24);\n  border-color: transparent; color: #0b0b0d; font-size: .9rem;\n}\n.rmap-title {\n  font-family: var(--font-body); font-weight: 600;\n  font-size: .88rem; color: var(--text-primary); margin-bottom: .4rem; line-height: 1.3;\n}\n.rmap-desc {\n  font-family: var(--font-body); font-weight: 300;\n  font-size: .75rem; color: var(--text-muted); line-height: 1.55;\n}\n.rmap-badge {\n  display: inline-block; margin-top: .6rem;\n  font-family: var(--font-mono); font-size: .6rem;\n  letter-spacing: .12em; text-transform: uppercase;\n  color: var(--orange); background: var(--orange-dim);\n  border: 1px solid rgba(255,153,0,.2); padding: .15rem .5rem; border-radius: 100px;\n}\n.rmap-badge.green { color: var(--sage); background: var(--sage-dim); border-color: rgba(110,231,183,.2); }\n\n/* ═════════════ MODULES ═════════════ */\n.modules-bg { background: var(--bg); }\n\n.modules-grid {\n  display: grid; grid-template-columns: 1fr 1fr;\n  gap: 1px; background: var(--border);\n  border: 1px solid var(--border);\n  border-radius: var(--radius-lg); overflow: hidden;\n}\n@media(max-width:720px) { .modules-grid { grid-template-columns: 1fr; } }\n\n.mod-card {\n  background: var(--bg-card); padding: 2.6rem;\n  position: relative; overflow: hidden;\n  transition: background .3s; cursor: default;\n}\n.mod-card:hover { background: var(--bg-card-hover); }\n\n.mod-card::before {\n  content: '';\n  position: absolute; top: 0; left: 0; right: 0; height: 2px;\n  background: var(--mc-accent, linear-gradient(90deg, var(--orange), var(--amber)));\n  transform: scaleX(0); transform-origin: left; transition: transform .4s ease;\n}\n.mod-card:hover::before { transform: scaleX(1); }\n.mod-card::after {\n  content: '';\n  position: absolute; top: -40px; right: -40px;\n  width: 200px; height: 200px; border-radius: 50%;\n  background: radial-gradient(ellipse, var(--mc-glow, rgba(255,153,0,.05)) 0%, transparent 70%);\n  pointer-events: none; transition: opacity .4s; opacity: 0;\n}\n.mod-card:hover::after { opacity: 1; }\n\n.mc-orange { --mc-accent: linear-gradient(90deg,#FF9900,#fbbf24); --mc-glow: rgba(255,153,0,.06); }\n.mc-sage   { --mc-accent: linear-gradient(90deg,#6ee7b7,#34d399);  --mc-glow: rgba(110,231,183,.05); }\n.mc-blue   { --mc-accent: linear-gradient(90deg,#38bdf8,#67e8f9);  --mc-glow: rgba(56,189,248,.05); }\n.mc-amber  { --mc-accent: linear-gradient(90deg,#fbbf24,#f59e0b);  --mc-glow: rgba(251,191,36,.05); }\n\n.mod-wm {\n  position: absolute; bottom: -14px; right: 8px;\n  font-family: var(--font-display); font-size: 6rem; font-weight: 700;\n  line-height: 1; color: rgba(255,153,0,.04);\n  user-select: none; pointer-events: none; letter-spacing: -.04em;\n}\n.mod-phase {\n  font-family: var(--font-mono); font-size: .62rem;\n  letter-spacing: .18em; text-transform: uppercase;\n  color: var(--text-dim); margin-bottom: .8rem; display: block;\n}\n.mod-head {\n  display: flex; align-items: flex-start; gap: 1rem; margin-bottom: 1.2rem;\n}\n.mod-ico {\n  width: 48px; height: 48px; flex-shrink: 0; border-radius: var(--radius-md);\n  display: flex; align-items: center; justify-content: center; font-size: 1.5rem;\n  background: var(--orange-dim); border: 1px solid rgba(255,153,0,.22);\n}\n.mc-sage  .mod-ico { background: var(--sage-dim); border-color: rgba(110,231,183,.2); }\n.mc-blue  .mod-ico { background: rgba(56,189,248,.08); border-color: rgba(56,189,248,.18); }\n.mc-amber .mod-ico { background: var(--amber-dim); border-color: rgba(251,191,36,.2); }\n\n.mod-num {\n  font-family: var(--font-mono); font-size: .62rem;\n  color: var(--orange); letter-spacing: .12em; margin-bottom: .2rem; display: block;\n}\n.mc-sage .mod-num  { color: var(--sage); }\n.mc-blue .mod-num  { color: #38bdf8; }\n.mc-amber .mod-num { color: var(--amber); }\n\n.mod-name {\n  font-family: var(--font-body); font-size: 1.15rem; font-weight: 600;\n  color: var(--text-primary); line-height: 1.2;\n}\n.mod-desc {\n  font-family: var(--font-body); font-weight: 300;\n  font-size: .9rem; color: var(--text-secondary); line-height: 1.7; margin-bottom: 1.5rem;\n}\n.mod-learns {\n  list-style: none; display: flex; flex-direction: column; gap: .5rem;\n}\n.mod-learns li {\n  font-family: var(--font-body); font-size: .82rem;\n  color: var(--text-muted); font-weight: 400;\n  display: flex; align-items: flex-start; gap: .6rem; line-height: 1.4;\n}\n.mod-learns li::before {\n  content: '▸'; color: var(--orange); font-size: .65rem; margin-top: .15rem; flex-shrink: 0;\n}\n.mc-sage  .mod-learns li::before { color: var(--sage); }\n.mc-blue  .mod-learns li::before { color: #38bdf8; }\n.mc-amber .mod-learns li::before { color: var(--amber); }\n\n.mod-footer {\n  margin-top: 1.8rem; padding-top: 1.2rem;\n  border-top: 1px solid var(--border);\n  display: flex; align-items: center; justify-content: space-between;\n}\n.mod-duration { font-family: var(--font-mono); font-size: .67rem; color: var(--text-dim); letter-spacing: .1em; }\n.mod-level {\n  font-family: var(--font-mono); font-size: .62rem;\n  letter-spacing: .14em; text-transform: uppercase;\n  padding: .2rem .65rem; border-radius: 100px;\n  background: var(--orange-dim); border: 1px solid rgba(255,153,0,.2); color: var(--orange);\n}\n.mc-sage  .mod-level { background: var(--sage-dim); border-color: rgba(110,231,183,.2); color: var(--sage); }\n.mc-blue  .mod-level { background: rgba(56,189,248,.08); border-color: rgba(56,189,248,.18); color: #38bdf8; }\n.mc-amber .mod-level { background: var(--amber-dim); border-color: rgba(251,191,36,.2); color: var(--amber); }\n\n/* ═════════════ AWS SERVICES ═════════════ */\n.services-section { background: var(--bg-surface); }\n\n.svc-categories {\n  display: grid; grid-template-columns: repeat(3,1fr);\n  gap: 1.5rem; margin-top: 3rem;\n}\n@media(max-width:800px) { .svc-categories { grid-template-columns: repeat(2,1fr); } }\n@media(max-width:500px) { .svc-categories { grid-template-columns: 1fr; } }\n\n.svc-cat-card {\n  background: var(--bg-card); border: 1px solid var(--border);\n  border-radius: var(--radius-md); padding: 1.6rem;\n  transition: border-color .25s, transform .25s;\n  opacity: 0; animation: cardIn .5s ease forwards;\n}\n.svc-cat-card:hover { border-color: var(--border-mid); transform: translateY(-3px); }\n.svc-cat-card:nth-child(1){animation-delay:.05s}\n.svc-cat-card:nth-child(2){animation-delay:.12s}\n.svc-cat-card:nth-child(3){animation-delay:.19s}\n.svc-cat-card:nth-child(4){animation-delay:.26s}\n.svc-cat-card:nth-child(5){animation-delay:.33s}\n.svc-cat-card:nth-child(6){animation-delay:.40s}\n\n@keyframes cardIn {\n  from { opacity: 0; transform: translateY(16px); }\n  to   { opacity: 1; transform: translateY(0); }\n}\n.svc-cat-header {\n  display: flex; align-items: center; gap: .7rem;\n  margin-bottom: 1rem; padding-bottom: .8rem; border-bottom: 1px solid var(--border);\n}\n.svc-cat-icon {\n  width: 30px; height: 30px; border-radius: 6px;\n  background: var(--orange-dim); border: 1px solid rgba(255,153,0,.18);\n  display: flex; align-items: center; justify-content: center; font-size: .9rem; flex-shrink: 0;\n}\n.svc-cat-name { font-family: var(--font-body); font-weight: 600; font-size: .82rem; color: var(--text-primary); }\n.svc-list { display: flex; flex-wrap: wrap; gap: .4rem; }\n.svc-tag {\n  font-family: var(--font-mono); font-size: .65rem; color: var(--text-muted);\n  background: rgba(255,255,255,.03); border: 1px solid var(--border-subtle);\n  padding: .2rem .55rem; border-radius: 3px; transition: color .2s, border-color .2s;\n}\n.svc-cat-card:hover .svc-tag { color: var(--orange); border-color: rgba(255,153,0,.2); }\n\n/* ═════════════ PROJECTS ═════════════ */\n.projects-section { background: var(--bg); }\n\n.projects-grid {\n  display: grid; grid-template-columns: repeat(3,1fr);\n  gap: 1.2rem; margin-top: 3rem;\n}\n@media(max-width:800px) { .projects-grid { grid-template-columns: repeat(2,1fr); } }\n@media(max-width:500px) { .projects-grid { grid-template-columns: 1fr; } }\n\n.proj-card {\n  background: var(--bg-card); border: 1px solid var(--border);\n  border-radius: var(--radius-md); padding: 1.8rem;\n  transition: all .25s ease; cursor: default; position: relative; overflow: hidden;\n}\n.proj-card:hover { border-color: var(--border-mid); transform: translateY(-3px); box-shadow: var(--shadow-card); }\n.proj-card::before {\n  content: '';\n  position: absolute; bottom: 0; left: 0; right: 0; height: 1.5px;\n  background: linear-gradient(90deg, transparent, var(--orange), transparent);\n  transform: scaleX(0); transition: transform .35s ease;\n}\n.proj-card:hover::before { transform: scaleX(1); }\n.proj-num { font-family: var(--font-mono); font-size: .62rem; letter-spacing: .18em; text-transform: uppercase; color: var(--text-dim); margin-bottom: .8rem; display: block; }\n.proj-name { font-family: var(--font-body); font-weight: 600; font-size: .95rem; color: var(--text-primary); margin-bottom: .6rem; line-height: 1.3; }\n.proj-desc { font-family: var(--font-body); font-weight: 300; font-size: .8rem; color: var(--text-muted); line-height: 1.6; margin-bottom: 1rem; }\n.proj-tags { display: flex; flex-wrap: wrap; gap: .35rem; }\n.proj-tag { font-family: var(--font-mono); font-size: .6rem; color: var(--orange); background: var(--orange-dim); border: 1px solid rgba(255,153,0,.18); padding: .18rem .5rem; border-radius: 3px; }\n\n/* ═════════════ UPCOMING CSPs ═════════════ */\n.teaser-section { background: var(--bg-surface); border-top: 1px solid var(--border); border-bottom: 1px solid var(--border); }\n.teaser-row { display: flex; flex-wrap: wrap; gap: 1rem; margin-top: 2.5rem; }\n.teaser-card {\n  flex: 1; min-width: 180px; padding: 1.4rem 1.6rem;\n  background: var(--bg-card); border: 1px solid var(--border);\n  border-radius: var(--radius-md); position: relative; overflow: hidden; cursor: default;\n}\n.teaser-card.active { border-color: var(--border-bright); background: var(--bg-elevated); }\n.teaser-card.active::before {\n  content: '';\n  position: absolute; top: 0; left: 0; right: 0; height: 2px;\n  background: linear-gradient(90deg, var(--orange), var(--amber));\n}\n.teaser-card .t-logo { font-family: var(--font-body); font-size: 1.1rem; font-weight: 700; margin-bottom: .3rem; }\n.teaser-card.active .t-logo     { color: var(--orange); }\n.teaser-card:not(.active) .t-logo { color: var(--text-muted); }\n.teaser-card .t-status { font-family: var(--font-mono); font-size: .62rem; letter-spacing: .14em; text-transform: uppercase; }\n.teaser-card.active .t-status     { color: var(--sage); }\n.teaser-card:not(.active) .t-status { color: var(--text-dim); }\n.teaser-card .t-info { font-family: var(--font-body); font-weight: 300; font-size: .78rem; color: var(--text-muted); line-height: 1.5; margin-top: .4rem; }\n\n/* ═════════════ CTA ═════════════ */\n.cta-section {\n  position: relative; overflow: hidden;\n  padding: clamp(5rem,10vw,9rem) clamp(1.5rem,7vw,8rem);\n  text-align: center; background: var(--bg); z-index: 1;\n}\n.cta-section::before {\n  content: ''; position: absolute; inset: 0; pointer-events: none;\n  background:\n    radial-gradient(ellipse 60% 50% at 50% 0%, rgba(255,153,0,.07) 0%, transparent 70%),\n    radial-gradient(ellipse 40% 60% at 20% 100%, rgba(110,231,183,.04) 0%, transparent 60%),\n    radial-gradient(ellipse 40% 60% at 80% 100%, rgba(251,191,36,.04) 0%, transparent 60%);\n}\n.cta-section::after {\n  content: ''; position: absolute; inset: 0; pointer-events: none;\n  background-image: linear-gradient(135deg, transparent 49.5%, rgba(255,153,0,.04) 49.5%, rgba(255,153,0,.04) 50.5%, transparent 50.5%);\n  background-size: 80px 80px; opacity: .5;\n}\n.cta-inner { position: relative; z-index: 2; }\n.cta-eyebrow {\n  display: inline-flex; align-items: center; gap: .6rem;\n  font-family: var(--font-mono); font-size: .68rem;\n  letter-spacing: .2em; text-transform: uppercase;\n  color: var(--orange); background: var(--orange-dim);\n  border: 1px solid var(--border-mid);\n  padding: .38rem 1.1rem; border-radius: 100px; margin-bottom: 2.2rem;\n}\n.cta-title {\n  font-family: var(--font-display) !important;\n  font-size: clamp(2.5rem,6vw,5rem) !important;\n  font-weight: 700 !important; line-height: 1.05 !important;\n  color: var(--text-primary) !important;\n  letter-spacing: -.025em; margin: 0 auto 1.2rem !important; max-width: 22ch;\n}\n.cta-title em { font-style: italic; color: var(--orange); }\n.cta-sub {\n  font-family: var(--font-body); font-weight: 300;\n  font-size: 1.05rem; color: var(--text-secondary);\n  max-width: 48ch; margin: 0 auto 3rem; line-height: 1.7;\n}\n.cta-actions { display: flex; flex-wrap: wrap; gap: 1rem; justify-content: center; }\n\n@media(max-width:700px) {\n  .hero { padding: 5rem 1.5rem 3rem; }\n  .hero-stats { gap: 1.8rem; }\n}\n</style>\n\n<div class=\"aws-page\">\n\n<!-- ══ HERO ══ -->\n<section class=\"hero\">\n  <div class=\"hero-glow-2\"></div>\n  <div class=\"hero-inner\">\n    <div class=\"aws-badge\">\n      <span class=\"badge-pulse\"></span>\n      AWS Cloud Training — Cohort Open\n    </div>\n\n    <h1 class=\"hero-title\">\n      Master<br>\n      <span class=\"line-orange\">Amazon</span><br>\n      <span class=\"line-italic\">Web Services</span>\n    </h1>\n\n    <p class=\"hero-desc\">\n      A structured, practitioner-built program covering cloud fundamentals,\n      core AWS services, Docker containerisation, and production deployment —\n      from absolute zero to job-ready.\n    </p>\n    <div class=\"hero-note\">Starts with cloud basics. No prior experience required.</div>\n\n    <div class=\"hero-cta\">\n      <a href=\"/contact.qmd\" class=\"btn-aws\">\n        <svg width=\"16\" height=\"16\" viewBox=\"0 0 16 16\" fill=\"none\"><path d=\"M3 8h10M9 4l4 4-4 4\" stroke=\"currentColor\" stroke-width=\"1.5\" stroke-linecap=\"round\" stroke-linejoin=\"round\"/></svg>\n        Enroll Now\n      </a>\n      <a href=\"#modules\" class=\"btn-outline-aws\">Browse Curriculum</a>\n    </div>\n\n    <div class=\"hero-stats\">\n      <div class=\"h-stat\">\n        <span class=\"h-stat-num\">5<span>+</span></span>\n        <span class=\"h-stat-label\">Core Modules</span>\n      </div>\n      <div class=\"h-stat\">\n        <span class=\"h-stat-num\">10<span>wk</span></span>\n        <span class=\"h-stat-label\">Program Length</span>\n      </div>\n      <div class=\"h-stat\">\n        <span class=\"h-stat-num\">SAA<span>-C03</span></span>\n        <span class=\"h-stat-label\">Cert Aligned</span>\n      </div>\n    </div>\n  </div>\n\n  <div class=\"hero-services\">\n    <div class=\"svc-pill\"><div class=\"svc-icon\">☁️</div><div><div class=\"svc-name\">EC2</div><div class=\"svc-cat\">Compute</div></div></div>\n    <div class=\"svc-pill\"><div class=\"svc-icon\">🪣</div><div><div class=\"svc-name\">S3</div><div class=\"svc-cat\">Storage</div></div></div>\n    <div class=\"svc-pill\"><div class=\"svc-icon docker\">🐳</div><div><div class=\"svc-name\">Docker</div><div class=\"svc-cat\">Containers</div></div></div>\n    <div class=\"svc-pill\"><div class=\"svc-icon\">🔒</div><div><div class=\"svc-name\">IAM</div><div class=\"svc-cat\">Identity &amp; Access</div></div></div>\n    <div class=\"svc-pill\"><div class=\"svc-icon\">🌐</div><div><div class=\"svc-name\">VPC</div><div class=\"svc-cat\">Networking</div></div></div>\n    <div class=\"svc-pill\"><div class=\"svc-icon green\">λ</div><div><div class=\"svc-name\">Lambda</div><div class=\"svc-cat\">Serverless</div></div></div>\n    <div class=\"svc-pill\"><div class=\"svc-icon red\">🗄️</div><div><div class=\"svc-name\">RDS</div><div class=\"svc-cat\">Databases</div></div></div>\n  </div>\n</section>\n\n<!-- ══ STRIP ══ -->\n<div class=\"divider-strip\">\n  <span class=\"strip-item\">Cloud Fundamentals</span><div class=\"strip-divider\"></div>\n  <span class=\"strip-item\">AWS Core Services</span><div class=\"strip-divider\"></div>\n  <span class=\"strip-item\">Docker &amp; Containers</span><div class=\"strip-divider\"></div>\n  <span class=\"strip-item\">Web Deployment</span><div class=\"strip-divider\"></div>\n  <span class=\"strip-item\">Serverless &amp; Architecture</span>\n</div>\n\n<!-- ══ ROADMAP ══ -->\n<section class=\"roadmap-section\">\n  <div class=\"s-wrap\">\n    <div class=\"s-label\">Learning Path</div>\n    <h2 class=\"s-title\">Your Road to <em>AWS Mastery</em></h2>\n    <p class=\"s-desc\">Five progressive phases — engineered so each week builds directly on the last, from cloud theory to certified practitioner.</p>\n    <div class=\"roadmap\">\n      <div class=\"rmap-step\">\n        <div class=\"rmap-num-wrap\">01</div>\n        <div class=\"rmap-title\">Cloud Computing Fundamentals</div>\n        <div class=\"rmap-desc\">IaaS, PaaS, SaaS, cloud economics, and the why behind cloud migration</div>\n        <span class=\"rmap-badge\">Weeks 1–2</span>\n      </div>\n      <div class=\"rmap-step\">\n        <div class=\"rmap-num-wrap\">02</div>\n        <div class=\"rmap-title\">AWS Core: Compute, Storage &amp; Networking</div>\n        <div class=\"rmap-desc\">EC2, S3, VPC, IAM — launching and securing real infrastructure</div>\n        <span class=\"rmap-badge\">Weeks 3–4</span>\n      </div>\n      <div class=\"rmap-step\">\n        <div class=\"rmap-num-wrap\">03</div>\n        <div class=\"rmap-title\">Docker &amp; Containerisation</div>\n        <div class=\"rmap-desc\">Build images, compose multi-service apps, and push to ECR</div>\n        <span class=\"rmap-badge\">Weeks 5–6</span>\n      </div>\n      <div class=\"rmap-step\">\n        <div class=\"rmap-num-wrap\">04</div>\n        <div class=\"rmap-title\">Web Deployment &amp; Serverless</div>\n        <div class=\"rmap-desc\">Nginx on EC2, SSL, Lambda, API Gateway, and event-driven patterns</div>\n        <span class=\"rmap-badge\">Weeks 7–9</span>\n      </div>\n      <div class=\"rmap-step step-final\">\n        <div class=\"rmap-num-wrap\">✦</div>\n        <div class=\"rmap-title\">Capstone + Certification Prep</div>\n        <div class=\"rmap-desc\">Deploy a full production app and prepare for SAA-C03</div>\n        <span class=\"rmap-badge green\">Week 10 · Cert Ready</span>\n      </div>\n    </div>\n  </div>\n</section>\n\n<!-- ══ MODULES ══ -->\n<section class=\"modules-bg\">\n  <div class=\"s-wrap\" id=\"modules\">\n    <div class=\"s-label\">Curriculum</div>\n    <h2 class=\"s-title\">Five <em>Core Modules</em></h2>\n    <p class=\"s-desc\">Each module is a self-contained, hands-on unit with labs on real AWS infrastructure — not simulated environments.</p>\n\n    <div class=\"modules-grid\">\n\n      <div class=\"mod-card mc-orange\">\n        <div class=\"mod-wm\">01</div>\n        <span class=\"mod-phase\">Module 01 · Foundation</span>\n        <div class=\"mod-head\">\n          <div class=\"mod-ico\">☁️</div>\n          <div><span class=\"mod-num\">Phase 1</span><div class=\"mod-name\">Cloud Computing Fundamentals</div></div>\n        </div>\n        <p class=\"mod-desc\">Build the mental model every cloud practitioner needs. Understand how cloud providers work, what you pay for, and why cloud has replaced on-premise infrastructure in modern engineering.</p>\n        <ul class=\"mod-learns\">\n          <li>IaaS, PaaS &amp; SaaS service models explained</li>\n          <li>Cloud economics: CapEx vs OpEx, pay-as-you-go</li>\n          <li>AWS global infrastructure: Regions &amp; Availability Zones</li>\n          <li>Shared Responsibility Model &amp; compliance basics</li>\n          <li>AWS Management Console, CLI &amp; SDK overview</li>\n        </ul>\n        <div class=\"mod-footer\">\n          <span class=\"mod-duration\">⏱ Weeks 1–2 · ~8 hrs</span>\n          <span class=\"mod-level\">Beginner</span>\n        </div>\n      </div>\n\n      <div class=\"mod-card mc-sage\">\n        <div class=\"mod-wm\">02</div>\n        <span class=\"mod-phase\">Module 02 · AWS Core</span>\n        <div class=\"mod-head\">\n          <div class=\"mod-ico\">⚙️</div>\n          <div><span class=\"mod-num\">Phase 2</span><div class=\"mod-name\">AWS Compute, Storage &amp; Networking</div></div>\n        </div>\n        <p class=\"mod-desc\">Get hands on with the services that power 70% of cloud workloads. Launch EC2 instances, configure secure networks, store objects in S3, and lock everything down with IAM.</p>\n        <ul class=\"mod-learns\">\n          <li>EC2: instance types, AMIs, user-data, key pairs</li>\n          <li>S3: buckets, policies, versioning &amp; static hosting</li>\n          <li>VPC: subnets, route tables, internet &amp; NAT gateways</li>\n          <li>Security Groups &amp; NACLs for layered defence</li>\n          <li>IAM: users, roles, policies &amp; least-privilege design</li>\n        </ul>\n        <div class=\"mod-footer\">\n          <span class=\"mod-duration\">⏱ Weeks 3–4 · ~10 hrs</span>\n          <span class=\"mod-level\">Intermediate</span>\n        </div>\n      </div>\n\n      <div class=\"mod-card mc-blue\">\n        <div class=\"mod-wm\">03</div>\n        <span class=\"mod-phase\">Module 03 · Containers</span>\n        <div class=\"mod-head\">\n          <div class=\"mod-ico\">🐳</div>\n          <div><span class=\"mod-num\">Phase 3</span><div class=\"mod-name\">Docker &amp; Containerisation on AWS</div></div>\n        </div>\n        <p class=\"mod-desc\">Package your applications once, run them anywhere. Master Docker from first principles and integrate containers natively into the AWS ecosystem using ECR and ECS.</p>\n        <ul class=\"mod-learns\">\n          <li>Docker architecture: images, containers &amp; volumes</li>\n          <li>Writing production-grade Dockerfiles &amp; .dockerignore</li>\n          <li>Docker Compose for multi-container local dev</li>\n          <li>Amazon ECR: building, tagging &amp; pushing images</li>\n          <li>Introduction to ECS &amp; Fargate for managed containers</li>\n        </ul>\n        <div class=\"mod-footer\">\n          <span class=\"mod-duration\">⏱ Weeks 5–6 · ~10 hrs</span>\n          <span class=\"mod-level\">Intermediate</span>\n        </div>\n      </div>\n\n      <div class=\"mod-card mc-amber\">\n        <div class=\"mod-wm\">04</div>\n        <span class=\"mod-phase\">Module 04 · Deployment</span>\n        <div class=\"mod-head\">\n          <div class=\"mod-ico\">🌐</div>\n          <div><span class=\"mod-num\">Phase 4</span><div class=\"mod-name\">Web Deployment, SSL &amp; Serverless</div></div>\n        </div>\n        <p class=\"mod-desc\">Take real applications live. Configure Nginx as a reverse proxy on EC2, automate SSL with Let's Encrypt, build serverless APIs with Lambda, and connect services with event-driven patterns.</p>\n        <ul class=\"mod-learns\">\n          <li>Nginx reverse proxy &amp; virtual host configuration</li>\n          <li>SSL/TLS with Certbot + Let's Encrypt on EC2</li>\n          <li>Route 53: DNS, A/CNAME records &amp; health checks</li>\n          <li>AWS Lambda: writing, deploying &amp; testing functions</li>\n          <li>API Gateway: REST APIs, triggers &amp; CORS setup</li>\n        </ul>\n        <div class=\"mod-footer\">\n          <span class=\"mod-duration\">⏱ Weeks 7–8 · ~10 hrs</span>\n          <span class=\"mod-level\">Intermediate</span>\n        </div>\n      </div>\n\n      <div class=\"mod-card mc-orange\" style=\"grid-column: 1 / -1;\">\n        <div class=\"mod-wm\" style=\"font-size:8rem;right:20px;\">05</div>\n        <span class=\"mod-phase\">Module 05 · Architecture</span>\n        <div class=\"mod-head\">\n          <div class=\"mod-ico\">🏗️</div>\n          <div><span class=\"mod-num\">Phase 5 · Capstone</span><div class=\"mod-name\">Cloud Architecture, Databases &amp; Certification Prep</div></div>\n        </div>\n        <div style=\"display:grid;grid-template-columns:1fr 1fr;gap:2rem;flex-wrap:wrap;\">\n          <p class=\"mod-desc\">Tie everything together. Design scalable, fault-tolerant architectures using AWS Well-Architected Framework pillars. Add managed databases, caching, and monitoring — then build a complete capstone project from scratch.</p>\n          <ul class=\"mod-learns\">\n            <li>RDS (PostgreSQL / MySQL) setup, backups &amp; replicas</li>\n            <li>ElastiCache &amp; DynamoDB for high-performance data</li>\n            <li>Load Balancers &amp; Auto Scaling Groups</li>\n            <li>CloudWatch metrics, alarms &amp; logging</li>\n            <li>Well-Architected Framework: 6 pillars review</li>\n            <li>SAA-C03 exam strategy &amp; mock assessment</li>\n          </ul>\n        </div>\n        <div class=\"mod-footer\" style=\"margin-top:1.4rem;\">\n          <span class=\"mod-duration\">⏱ Weeks 9–10 · ~12 hrs</span>\n          <span class=\"mod-level\">Advanced</span>\n        </div>\n      </div>\n\n    </div>\n  </div>\n</section>\n\n<!-- ══ AWS SERVICES ══ -->\n<section class=\"services-section\">\n  <div class=\"s-wrap\">\n    <div class=\"s-label\">Services</div>\n    <h2 class=\"s-title\">AWS Services You'll <em>Use</em></h2>\n    <p class=\"s-desc\">Hands-on labs with the most in-demand AWS services — grouped by category so you understand how they interconnect.</p>\n\n    <div class=\"svc-categories\">\n      <div class=\"svc-cat-card\">\n        <div class=\"svc-cat-header\"><div class=\"svc-cat-icon\">⚡</div><span class=\"svc-cat-name\">Compute</span></div>\n        <div class=\"svc-list\"><span class=\"svc-tag\">EC2</span><span class=\"svc-tag\">Lambda</span><span class=\"svc-tag\">ECS Fargate</span><span class=\"svc-tag\">Elastic Beanstalk</span><span class=\"svc-tag\">Auto Scaling</span></div>\n      </div>\n      <div class=\"svc-cat-card\">\n        <div class=\"svc-cat-header\"><div class=\"svc-cat-icon\">🗃️</div><span class=\"svc-cat-name\">Storage &amp; Databases</span></div>\n        <div class=\"svc-list\"><span class=\"svc-tag\">S3</span><span class=\"svc-tag\">EBS</span><span class=\"svc-tag\">RDS</span><span class=\"svc-tag\">DynamoDB</span><span class=\"svc-tag\">ElastiCache</span></div>\n      </div>\n      <div class=\"svc-cat-card\">\n        <div class=\"svc-cat-header\"><div class=\"svc-cat-icon\">🌐</div><span class=\"svc-cat-name\">Networking</span></div>\n        <div class=\"svc-list\"><span class=\"svc-tag\">VPC</span><span class=\"svc-tag\">Route 53</span><span class=\"svc-tag\">ALB / NLB</span><span class=\"svc-tag\">CloudFront</span><span class=\"svc-tag\">API Gateway</span></div>\n      </div>\n      <div class=\"svc-cat-card\">\n        <div class=\"svc-cat-header\"><div class=\"svc-cat-icon\">🔒</div><span class=\"svc-cat-name\">Security &amp; Identity</span></div>\n        <div class=\"svc-list\"><span class=\"svc-tag\">IAM</span><span class=\"svc-tag\">Security Groups</span><span class=\"svc-tag\">NACLs</span><span class=\"svc-tag\">KMS</span><span class=\"svc-tag\">Secrets Manager</span></div>\n      </div>\n      <div class=\"svc-cat-card\">\n        <div class=\"svc-cat-header\"><div class=\"svc-cat-icon\">📊</div><span class=\"svc-cat-name\">Monitoring &amp; Ops</span></div>\n        <div class=\"svc-list\"><span class=\"svc-tag\">CloudWatch</span><span class=\"svc-tag\">CloudTrail</span><span class=\"svc-tag\">AWS Config</span><span class=\"svc-tag\">SNS</span><span class=\"svc-tag\">SQS</span></div>\n      </div>\n      <div class=\"svc-cat-card\">\n        <div class=\"svc-cat-header\"><div class=\"svc-cat-icon\">🐳</div><span class=\"svc-cat-name\">Containers</span></div>\n        <div class=\"svc-list\"><span class=\"svc-tag\">Docker</span><span class=\"svc-tag\">ECR</span><span class=\"svc-tag\">ECS</span><span class=\"svc-tag\">Fargate</span><span class=\"svc-tag\">Docker Compose</span></div>\n      </div>\n    </div>\n  </div>\n</section>\n\n<!-- ══ PROJECTS ══ -->\n<section class=\"projects-section\">\n  <div class=\"s-wrap\">\n    <div class=\"s-label\">Hands-On Projects</div>\n    <h2 class=\"s-title\">Build <em>Real Things</em></h2>\n    <p class=\"s-desc\">Every module culminates in a project deployed to live AWS infrastructure — not sandboxed demos.</p>\n\n    <div class=\"projects-grid\">\n      <div class=\"proj-card\">\n        <span class=\"proj-num\">Project 01</span>\n        <div class=\"proj-name\">Secure Multi-Tier VPC Architecture</div>\n        <div class=\"proj-desc\">Design and deploy a VPC with public/private subnets, NAT gateways, bastion host, and security group rules mirroring production setups.</div>\n        <div class=\"proj-tags\"><span class=\"proj-tag\">VPC</span><span class=\"proj-tag\">EC2</span><span class=\"proj-tag\">IAM</span></div>\n      </div>\n      <div class=\"proj-card\">\n        <span class=\"proj-num\">Project 02</span>\n        <div class=\"proj-name\">Containerised App on ECS Fargate</div>\n        <div class=\"proj-desc\">Dockerise a web application, push to ECR, and deploy as a managed ECS Fargate service behind an Application Load Balancer.</div>\n        <div class=\"proj-tags\"><span class=\"proj-tag\">Docker</span><span class=\"proj-tag\">ECR</span><span class=\"proj-tag\">ECS</span></div>\n      </div>\n      <div class=\"proj-card\">\n        <span class=\"proj-num\">Project 03</span>\n        <div class=\"proj-name\">Full-Stack Serverless API</div>\n        <div class=\"proj-desc\">Build a REST API using Lambda + API Gateway backed by DynamoDB, with IAM-secured endpoints, CloudWatch logging, and a custom domain via Route 53.</div>\n        <div class=\"proj-tags\"><span class=\"proj-tag\">Lambda</span><span class=\"proj-tag\">API Gateway</span><span class=\"proj-tag\">DynamoDB</span></div>\n      </div>\n      <div class=\"proj-card\">\n        <span class=\"proj-num\">Project 04</span>\n        <div class=\"proj-name\">Static Website with CDN &amp; SSL</div>\n        <div class=\"proj-desc\">Host a static site on S3, front it with CloudFront for global CDN, attach an ACM SSL certificate, and configure Route 53 DNS.</div>\n        <div class=\"proj-tags\"><span class=\"proj-tag\">S3</span><span class=\"proj-tag\">CloudFront</span><span class=\"proj-tag\">Route 53</span></div>\n      </div>\n      <div class=\"proj-card\">\n        <span class=\"proj-num\">Project 05</span>\n        <div class=\"proj-name\">Auto-Scaling Web Application</div>\n        <div class=\"proj-desc\">Deploy a web app across multiple AZs with an ALB, Auto Scaling Group with launch templates, RDS Multi-AZ, and CloudWatch alarms.</div>\n        <div class=\"proj-tags\"><span class=\"proj-tag\">ALB</span><span class=\"proj-tag\">ASG</span><span class=\"proj-tag\">RDS</span></div>\n      </div>\n      <div class=\"proj-card\">\n        <span class=\"proj-num\">Capstone</span>\n        <div class=\"proj-name\">Production-Grade Cloud Platform</div>\n        <div class=\"proj-desc\">Synthesise all five modules into a single full-stack platform: containers, databases, serverless functions, monitoring, and CI/CD basics.</div>\n        <div class=\"proj-tags\"><span class=\"proj-tag\">Full Stack</span><span class=\"proj-tag\">Portfolio</span><span class=\"proj-tag\">SAA-C03</span></div>\n      </div>\n    </div>\n  </div>\n</section>\n\n<!-- ══ UPCOMING CSPs ══ -->\n<section class=\"teaser-section\">\n  <div class=\"s-wrap\">\n    <div class=\"s-label\">Coming Soon</div>\n    <h2 class=\"s-title\">More <em>Cloud Providers</em> on the Way</h2>\n    <p class=\"s-desc\">AWS is just the beginning. Dedicated tracks for Google Cloud and Azure are currently being developed — with the same hands-on, practitioner-first approach.</p>\n    <div class=\"teaser-row\">\n      <div class=\"teaser-card active\">\n        <div class=\"t-logo\">Amazon Web Services</div>\n        <div class=\"t-status\">● Now Enrolling</div>\n        <div class=\"t-info\">Full curriculum live. Certification aligned to SAA-C03.</div>\n      </div>\n      <div class=\"teaser-card\">\n        <div class=\"t-logo\">Google Cloud Platform</div>\n        <div class=\"t-status\">◌ In Development</div>\n        <div class=\"t-info\">GCP Associate Cloud Engineer track — launching soon.</div>\n      </div>\n      <div class=\"teaser-card\">\n        <div class=\"t-logo\">Microsoft Azure</div>\n        <div class=\"t-status\">◌ Planned</div>\n        <div class=\"t-info\">AZ-900 &amp; AZ-104 aligned track coming later this year.</div>\n      </div>\n      <div class=\"teaser-card\">\n        <div class=\"t-logo\">Multi-Cloud Architecture</div>\n        <div class=\"t-status\">◌ Advanced Track</div>\n        <div class=\"t-info\">Advanced course on designing for multiple CSPs simultaneously.</div>\n      </div>\n    </div>\n  </div>\n</section>\n\n<!-- ══ CTA ══ -->\n<section class=\"cta-section\">\n  <div class=\"cta-inner\">\n    <div class=\"cta-eyebrow\"><span class=\"badge-pulse\"></span>Limited Seats Per Cohort</div>\n    <h2 class=\"cta-title\">Your first AWS project<br>goes live <em>this month.</em></h2>\n    <p class=\"cta-sub\">Structured training, real infrastructure, live projects you can put in a portfolio — and a clear path to your first AWS certification.</p>\n    <div class=\"cta-actions\">\n      <a href=\"/contact.qmd\" class=\"btn-aws\">\n        <svg width=\"16\" height=\"16\" viewBox=\"0 0 16 16\" fill=\"none\"><path d=\"M3 8h10M9 4l4 4-4 4\" stroke=\"currentColor\" stroke-width=\"1.5\" stroke-linecap=\"round\" stroke-linejoin=\"round\"/></svg>\n        Enroll in AWS Track\n      </a>\n      <a href=\"/contact.qmd\" class=\"btn-outline-aws\">Talk to an Advisor</a>\n    </div>\n  </div>\n</section>\n\n</div>\n```\n"},"formats":{"html":{"identifier":{"display-name":"HTML","target-format":"html","base-format":"html"},"execute":{"fig-width":7,"fig-height":5,"fig-format":"retina","fig-dpi":96,"df-print":"default","error":false,"eval":true,"cache":null,"freeze":"auto","echo":true,"output":true,"warning":true,"include":true,"keep-md":false,"keep-ipynb":false,"ipynb":null,"enabled":null,"daemon":null,"daemon-restart":false,"debug":false,"ipynb-filters":[],"ipynb-shell-interactivity":null,"plotly-connected":true,"engine":"markdown"},"render":{"keep-tex":false,"keep-typ":false,"keep-source":false,"keep-hidden":false,"prefer-html":false,"output-divs":true,"output-ext":"html","fig-align":"default","fig-pos":null,"fig-env":null,"code-fold":"none","code-overflow":"scroll","code-link":false,"code-line-numbers":false,"code-tools":false,"tbl-colwidths":"auto","merge-includes":true,"inline-includes":false,"preserve-yaml":false,"latex-auto-mk":true,"latex-auto-install":true,"latex-clean":true,"latex-min-runs":1,"latex-max-runs":10,"latex-makeindex":"makeindex","latex-makeindex-opts":[],"latex-tlmgr-opts":[],"latex-input-paths":[],"latex-output-dir":null,"link-external-icon":false,"link-external-newwindow":true,"self-contained-math":false,"format-resources":[],"notebook-links":true},"pandoc":{"standalone":true,"wrap":"none","default-image-extension":"png","to":"html","css":["../styles.css"],"toc":false,"include-in-header":{"text":"<link rel=\"preconnect\" href=\"https://fonts.googleapis.com\">\n<link rel=\"preconnect\" href=\"https://fonts.gstatic.com\" crossorigin>\n<link href=\"https://fonts.googleapis.com/css2?family=Cormorant+Garamond:ital,wght@0,400;0,600;0,700;1,400;1,600&family=IBM+Plex+Sans:wght@300;400;500;600&family=IBM+Plex+Mono:wght@400;500&display=swap\" rel=\"stylesheet\">\n"},"include-before-body":["../header.html"],"include-after-body":["../footer.html"],"output-file":"cloud (1).html"},"language":{"toc-title-document":"Table of contents","toc-title-website":"On this page","related-formats-title":"Other Formats","related-notebooks-title":"Notebooks","source-notebooks-prefix":"Source","other-links-title":"Other Links","code-links-title":"Code Links","launch-dev-container-title":"Launch Dev Container","launch-binder-title":"Launch Binder","article-notebook-label":"Article Notebook","notebook-preview-download":"Download Notebook","notebook-preview-download-src":"Download Source","notebook-preview-back":"Back to Article","manuscript-meca-bundle":"MECA Bundle","section-title-abstract":"Abstract","section-title-appendices":"Appendices","section-title-footnotes":"Footnotes","section-title-references":"References","section-title-reuse":"Reuse","section-title-copyright":"Copyright","section-title-citation":"Citation","appendix-attribution-cite-as":"For attribution, please cite this work as:","appendix-attribution-bibtex":"BibTeX citation:","appendix-view-license":"View License","title-block-author-single":"Author","title-block-author-plural":"Authors","title-block-affiliation-single":"Affiliation","title-block-affiliation-plural":"Affiliations","title-block-published":"Published","title-block-modified":"Modified","title-block-keywords":"Keywords","callout-tip-title":"Tip","callout-note-title":"Note","callout-warning-title":"Warning","callout-important-title":"Important","callout-caution-title":"Caution","code-summary":"Code","code-tools-menu-caption":"Code","code-tools-show-all-code":"Show All Code","code-tools-hide-all-code":"Hide All Code","code-tools-view-source":"View Source","code-tools-source-code":"Source Code","tools-share":"Share","tools-download":"Download","code-line":"Line","code-lines":"Lines","copy-button-tooltip":"Copy to Clipboard","copy-button-tooltip-success":"Copied!","repo-action-links-edit":"Edit this page","repo-action-links-source":"View source","repo-action-links-issue":"Report an issue","back-to-top":"Back to top","search-no-results-text":"No results","search-matching-documents-text":"matching documents","search-copy-link-title":"Copy link to search","search-hide-matches-text":"Hide additional matches","search-more-match-text":"more match in this document","search-more-matches-text":"more matches in this document","search-clear-button-title":"Clear","search-text-placeholder":"","search-detached-cancel-button-title":"Cancel","search-submit-button-title":"Submit","search-label":"Search","toggle-section":"Toggle section","toggle-sidebar":"Toggle sidebar navigation","toggle-dark-mode":"Toggle dark mode","toggle-reader-mode":"Toggle reader mode","toggle-navigation":"Toggle navigation","crossref-fig-title":"Figure","crossref-tbl-title":"Table","crossref-lst-title":"Listing","crossref-thm-title":"Theorem","crossref-lem-title":"Lemma","crossref-cor-title":"Corollary","crossref-prp-title":"Proposition","crossref-cnj-title":"Conjecture","crossref-def-title":"Definition","crossref-exm-title":"Example","crossref-exr-title":"Exercise","crossref-ch-prefix":"Chapter","crossref-apx-prefix":"Appendix","crossref-sec-prefix":"Section","crossref-eq-prefix":"Equation","crossref-lof-title":"List of Figures","crossref-lot-title":"List of Tables","crossref-lol-title":"List of Listings","environment-proof-title":"Proof","environment-remark-title":"Remark","environment-solution-title":"Solution","listing-page-order-by":"Order By","listing-page-order-by-default":"Default","listing-page-order-by-date-asc":"Oldest","listing-page-order-by-date-desc":"Newest","listing-page-order-by-number-desc":"High to Low","listing-page-order-by-number-asc":"Low to High","listing-page-field-date":"Date","listing-page-field-title":"Title","listing-page-field-description":"Description","listing-page-field-author":"Author","listing-page-field-filename":"File Name","listing-page-field-filemodified":"Modified","listing-page-field-subtitle":"Subtitle","listing-page-field-readingtime":"Reading Time","listing-page-field-wordcount":"Word Count","listing-page-field-categories":"Categories","listing-page-minutes-compact":"{0} min","listing-page-category-all":"All","listing-page-no-matches":"No matching items","listing-page-words":"{0} words","listing-page-filter":"Filter","draft":"Draft"},"metadata":{"lang":"en","fig-responsive":true,"quarto-version":"1.9.38","editor":"visual","engines":[{"path":"C:\\PROGRA~1\\Quarto\\share\\extension-subtrees\\julia-engine\\_extensions\\julia-engine\\julia-engine.js"}],"theme":"flatly","page-layout":"full","theme-toggle":false,"title":"AWS Cloud & Container Mastery"},"extensions":{"book":{"multiFile":true}}}},"projectFormats":["html"]}